Workbook

Sheet Data
A1: # | B1: Deal ID | C1: Deal Value | D1: Revenue LTM | E1: EBITDA LTM | F1: Entry Multiple | G1: EBITDA Margin
A2: Deal 1 | B2: =Screening!I2 -> IQTR1942758117 | C2: =Screening!F2 -> 9243.42 | D2: =Screening!L2 -> 30976.85 | E2: =Screening!N2 -> 5335.2 | F2: =C2/E2 -> 1.7325349 | G2: =100*(E2/D2) -> 17.223184
A3: Deal 2 | B3: =Screening!I3 -> IQTR1784746799 | C3: =Screening!F3 -> 72967.49 | D3: =Screening!L3 -> 12945 | E3: =Screening!N3 -> - | F3: =C3/E3 -> #VALUE! | G3: =E3/D3 -> #VALUE!
A4: Deal 3 | B4: =Screening!I4 -> IQTR1860930383 | C4: =Screening!F4 -> - | D4: =Screening!L4 -> 11615.16 | E4: =Screening!N4 -> 534.7 | F4: =C4/E4 -> #VALUE! | G4: =E4/D4 -> 0.046034665
A5: Deal 4 | B5: =Screening!I5 -> IQTR1944075963 | C5: =Screening!F5 -> 3000 | D5: =Screening!L5 -> 6000 | E5: =Screening!N5 -> - | F5: =C5/E5 -> #VALUE! | G5: =E5/D5 -> #VALUE!
A6: Deal 5 | B6: =Screening!I6 -> IQTR1867916120 | C6: =Screening!F6 -> 15396.69 | D6: =Screening!L6 -> 5564.5 | E6: =Screening!N6 -> 689.8 | F6: =C6/E6 -> 22.320513 | G6: =100*(E6/D6) -> 12.396442
A7: Deal 6 | B7: =Screening!I7 -> IQTR1912024769 | C7: =Screening!F7 -> - | D7: =Screening!L7 -> 5330.6 | E7: =Screening!N7 -> 776.9 | F7: =C7/E7 -> #VALUE! | G7: =E7/D7 -> 0.14574344
A8: Deal 7 | B8: =Screening!I8 -> IQTR1776383559 | C8: =Screening!F8 -> 478.06 | D8: =Screening!L8 -> 5157.45 | E8: =Screening!N8 -> 698.6 | F8: =C8/E8 -> 0.68431148 | G8: =100*(E8/D8) -> 13.545454
A9: Deal 8 | B9: =Screening!I9 -> IQTR1967911118 | C9: =Screening!F9 -> 4359.34 | D9: =Screening!L9 -> 4836.99 | E9: =Screening!N9 -> 766.3 | F9: =C9/E9 -> 5.6888164 | G9: =100*(E9/D9) -> 15.842497
A10: Deal 9 | B10: =Screening!I10 -> IQTR1955725309 | C10: =Screening!F10 -> 141.01 | D10: =Screening!L10 -> 4825.83 | E10: =Screening!N10 -> 10.6 | F10: =C10/E10 -> 13.30283 | G10: =100*(E10/D10) -> 0.21965133
A11: Deal 10 | B11: =Screening!I11 -> IQTR1863840995 | C11: =Screening!F11 -> - | D11: =Screening!L11 -> 4475 | E11: =Screening!N11 -> 776.9 | F11: =C11/E11 -> #VALUE! | G11: =E11/D11 -> 0.17360894
A12: Deal 11 | B12: =Screening!I12 -> IQTR1862954563 | C12: =Screening!F12 -> 129.05 | D12: =Screening!L12 -> 4475 | E12: =Screening!N12 -> 776.9 | F12: =C12/E12 -> 0.16610889 | G12: =100*(E12/D12) -> 17.360894
A13: Deal 12 | B13: =Screening!I13 -> IQTR1838306852 | C13: =Screening!F13 -> 70.67 | D13: =Screening!L13 -> 4301.36 | E13: =Screening!N13 -> 776.9 | F13: =C13/E13 -> 0.090964088 | G13: =100*(E13/D13) -> 18.061729
A14: Deal 13 | B14: =Screening!I14 -> IQTR1929482728 | C14: =Screening!F14 -> 174 | D14: =Screening!L14 -> 4145.17 | E14: =Screening!N14 -> 668.9 | F14: =C14/E14 -> 0.26012857 | G14: =100*(E14/D14) -> 16.136853
A15: Deal 14 | B15: =Screening!I15 -> IQTR1850957260 | C15: =Screening!F15 -> 1678.11 | D15: =Screening!L15 -> 4057.13 | E15: =Screening!N15 -> - | F15: =C15/E15 -> #VALUE! | G15: =E15/D15 -> #VALUE!
A16: Deal 15 | B16: =Screening!I16 -> IQTR1785931677 | C16: =Screening!F16 -> 66.77 | D16: =Screening!L16 -> 3926.97 | E16: =Screening!N16 -> 776.9 | F16: =C16/E16 -> 0.085944137 | G16: =100*(E16/D16) -> 19.783701
A17: Deal 16 | B17: =Screening!I17 -> IQTR1856318900 | C17: =Screening!F17 -> 30998.87 | D17: =Screening!L17 -> 3842.97 | E17: =Screening!N17 -> - | F17: =C17/E17 -> #VALUE! | G17: =E17/D17 -> #VALUE!
A18: Deal 17 | B18: =Screening!I18 -> IQTR1762042686 | C18: =Screening!F18 -> 102.35 | D18: =Screening!L18 -> 3841.83 | E18: =Screening!N18 -> 776.9 | F18: =C18/E18 -> 0.13174154 | G18: =100*(E18/D18) -> 20.222134
A19: Deal 18 | B19: =Screening!I19 -> IQTR1816233358 | C19: =Screening!F19 -> 45.4 | D19: =Screening!L19 -> 3694.6 | E19: =Screening!N19 -> 776.9 | F19: =C19/E19 -> 0.058437379 | G19: =100*(E19/D19) -> 21.027987
A20: Deal 19 | B20: =Screening!I20 -> IQTR1680643570 | C20: =Screening!F20 -> - | D20: =Screening!L20 -> 3311.12 | E20: =Screening!N20 -> 396 | F20: =C20/E20 -> #VALUE! | G20: =E20/D20 -> 0.11959699
A21: Deal 20 | B21: =Screening!I21 -> IQTR1765987121 | C21: =Screening!F21 -> 17182.11 | D21: =Screening!L21 -> 3217.17 | E21: =Screening!N21 -> - | F21: =C21/E21 -> #VALUE! | G21: =E21/D21 -> #VALUE!
A22: Deal 21 | B22: =Screening!I22 -> IQTR1853829677 | C22: =Screening!F22 -> - | D22: =Screening!L22 -> 3164.63 | E22: =Screening!N22 -> 396 | F22: =C22/E22 -> #VALUE! | G22: =E22/D22 -> 0.12513311
A23: Deal 22 | B23: =Screening!I23 -> IQTR1798157276 | C23: =Screening!F23 -> 6477.38 | D23: =Screening!L23 -> 2743.8 | E23: =Screening!N23 -> - | F23: =C23/E23 -> #VALUE! | G23: =E23/D23 -> #VALUE!
A24: Deal 23 | B24: =Screening!I24 -> IQTR1821576629 | C24: =Screening!F24 -> - | D24: =Screening!L24 -> 2659.43 | E24: =Screening!N24 -> 282.7 | F24: =C24/E24 -> #VALUE! | G24: =E24/D24 -> 0.10630097
A25: Deal 24 | B25: =Screening!I25 -> IQTR1868555623 | C25: =Screening!F25 -> 35791.48 | D25: =Screening!L25 -> 2583.1 | E25: =Screening!N25 -> 878 | F25: =C25/E25 -> 40.764784 | G25: =100*(E25/D25) -> 33.990167
A26: Deal 25 | B26: =Screening!I26 -> IQTR1902207620 | C26: =Screening!F26 -> 702 | D26: =Screening!L26 -> 2390.56 | E26: =Screening!N26 -> 209 | F26: =C26/E26 -> 3.3588517 | G26: =100*(E26/D26) -> 8.7427214
A27: Deal 26 | B27: =Screening!I27 -> IQTR1681724164 | C27: =Screening!F27 -> - | D27: =Screening!L27 -> 2377.81 | E27: =Screening!N27 -> 759.9 | F27: =C27/E27 -> #VALUE! | G27: =E27/D27 -> 0.31957978
A28: Deal 27 | B28: =Screening!I28 -> IQTR1890818396 | C28: =Screening!F28 -> 1239.77 | D28: =Screening!L28 -> 2178.56 | E28: =Screening!N28 -> 184.6 | F28: =C28/E28 -> 6.7159805 | G28: =100*(E28/D28) -> 8.4734871
A29: Deal 28 | B29: =Screening!I29 -> IQTR1802771200 | C29: =Screening!F29 -> - | D29: =Screening!L29 -> 2177.1 | E29: =Screening!N29 -> 282.7 | F29: =C29/E29 -> #VALUE! | G29: =E29/D29 -> 0.12985164
A30: Deal 29 | B30: =Screening!I30 -> IQTR1685463254 | C30: =Screening!F30 -> 2500 | D30: =Screening!L30 -> 2035 | E30: =Screening!N30 -> - | F30: =C30/E30 -> #VALUE! | G30: =E30/D30 -> #VALUE!
A31: Deal 30 | B31: =Screening!I31 -> IQTR1904331229 | C31: =Screening!F31 -> 2987.11 | D31: =Screening!L31 -> 2019.35 | E31: =Screening!N31 -> 184.6 | F31: =C31/E31 -> 16.181528 | G31: =100*(E31/D31) -> 9.1415555
A32: Deal 31 | B32: =Screening!I32 -> IQTR1773626089 | C32: =Screening!F32 -> - | D32: =Screening!L32 -> 2000 | E32: =Screening!N32 -> - | F32: =C32/E32 -> #VALUE! | G32: =E32/D32 -> #VALUE!
A33: Deal 32 | B33: =Screening!I33 -> IQTR1757348954 | C33: =Screening!F33 -> 20862.21 | D33: =Screening!L33 -> 1826 | E33: =Screening!N33 -> - | F33: =C33/E33 -> #VALUE! | G33: =E33/D33 -> #VALUE!
A34: Deal 33 | B34: =Screening!I34 -> IQTR1930420741 | C34: =Screening!F34 -> 1010.8 | D34: =Screening!L34 -> 1801.51 | E34: =Screening!N34 -> 100.2 | F34: =C34/E34 -> 10.087824 | G34: =100*(E34/D34) -> 5.5620008
A35: Deal 34 | B35: =Screening!I35 -> IQTR1772509697 | C35: =Screening!F35 -> 291.2 | D35: =Screening!L35 -> 1766.63 | E35: =Screening!N35 -> - | F35: =C35/E35 -> #VALUE! | G35: =E35/D35 -> #VALUE!
A36: Deal 35 | B36: =Screening!I36 -> IQTR1777417497 | C36: =Screening!F36 -> 8340.71 | D36: =Screening!L36 -> 1756.5 | E36: =Screening!N36 -> - | F36: =C36/E36 -> #VALUE! | G36: =E36/D36 -> #VALUE!
A37: Deal 36 | B37: =Screening!I37 -> IQTR1818826920 | C37: =Screening!F37 -> 6570.02 | D37: =Screening!L37 -> 1747 | E37: =Screening!N37 -> - | F37: =C37/E37 -> #VALUE! | G37: =E37/D37 -> #VALUE!
A38: Deal 37 | B38: =Screening!I38 -> IQTR1760525650 | C38: =Screening!F38 -> - | D38: =Screening!L38 -> 1734.66 | E38: =Screening!N38 -> - | F38: =C38/E38 -> #VALUE! | G38: =E38/D38 -> #VALUE!
A39: Deal 38 | B39: =Screening!I39 -> IQTR1945143029 | C39: =Screening!F39 -> 10097.75 | D39: =Screening!L39 -> 1655.31 | E39: =Screening!N39 -> 280.9 | F39: =C39/E39 -> 35.947846 | G39: =100*(E39/D39) -> 16.969631
A40: Deal 39 | B40: =Screening!I40 -> IQTR1888824933 | C40: =Screening!F40 -> 803.5 | D40: =Screening!L40 -> 1613.63 | E40: =Screening!N40 -> - | F40: =C40/E40 -> #VALUE! | G40: =E40/D40 -> #VALUE!
A41: Deal 40 | B41: =Screening!I41 -> IQTR1887815986 | C41: =Screening!F41 -> 2217.86 | D41: =Screening!L41 -> 1613.63 | E41: =Screening!N41 -> - | F41: =C41/E41 -> #VALUE! | G41: =E41/D41 -> #VALUE!
A42: Deal 41 | B42: =Screening!I42 -> IQTR1781572984 | C42: =Screening!F42 -> 14772.33 | D42: =Screening!L42 -> 1551.9 | E42: =Screening!N42 -> - | F42: =C42/E42 -> #VALUE! | G42: =E42/D42 -> #VALUE!
A43: Deal 42 | B43: =Screening!I43 -> IQTR1775144551 | C43: =Screening!F43 -> 92.94 | D43: =Screening!L43 -> 1526.16 | E43: =Screening!N43 -> 131.4 | F43: =C43/E43 -> 0.70730594 | G43: =100*(E43/D43) -> 8.6098443
A44: Deal 43 | B44: =Screening!I44 -> IQTR2000373976 | C44: =Screening!F44 -> 942.2 | D44: =Screening!L44 -> 1506.97 | E44: =Screening!N44 -> 483.1 | F44: =C44/E44 -> 1.9503208 | G44: =100*(E44/D44) -> 32.057705
A45: Deal 44 | B45: =Screening!I45 -> IQTR1903250285 | C45: =Screening!F45 -> 1967.76 | D45: =Screening!L45 -> 1484.46 | E45: =Screening!N45 -> 167 | F45: =C45/E45 -> 11.782994 | G45: =100*(E45/D45) -> 11.249882
A46: Deal 45 | B46: =Screening!I46 -> IQTR1829326219 | C46: =Screening!F46 -> 11166.16 | D46: =Screening!L46 -> 1458.63 | E46: =Screening!N46 -> - | F46: =C46/E46 -> #VALUE! | G46: =E46/D46 -> #VALUE!
A47: Deal 46 | B47: =Screening!I47 -> IQTR1788006790 | C47: =Screening!F47 -> 10989.54 | D47: =Screening!L47 -> 1428.88 | E47: =Screening!N47 -> - | F47: =C47/E47 -> #VALUE! | G47: =E47/D47 -> #VALUE!
A48: Deal 47 | B48: =Screening!I48 -> IQTR1981910022 | C48: =Screening!F48 -> - | D48: =Screening!L48 -> 1400.21 | E48: =Screening!N48 -> 66.3 | F48: =C48/E48 -> #VALUE! | G48: =E48/D48 -> 0.04735004
A49: Deal 48 | B49: =Screening!I49 -> IQTR1801227134 | C49: =Screening!F49 -> 4683.21 | D49: =Screening!L49 -> 1399.44 | E49: =Screening!N49 -> - | F49: =C49/E49 -> #VALUE! | G49: =E49/D49 -> #VALUE!
A50: Deal 49 | B50: =Screening!I50 -> IQTR1781913531 | C50: =Screening!F50 -> 7543.48 | D50: =Screening!L50 -> 1386.92 | E50: =Screening!N50 -> 750.3 | F50: =C50/E50 -> 10.053952 | G50: =100*(E50/D50) -> 54.09829
A51: Deal 50 | B51: =Screening!I51 -> IQTR1887698908 | C51: =Screening!F51 -> 4407.65 | D51: =Screening!L51 -> 1307.7 | E51: =Screening!N51 -> - | F51: =C51/E51 -> #VALUE! | G51: =E51/D51 -> #VALUE!
A52: Deal 51 | B52: =Screening!I52 -> IQTR1841667695 | C52: =Screening!F52 -> - | D52: =Screening!L52 -> 1304.5 | E52: =Screening!N52 -> 19 | F52: =C52/E52 -> #VALUE! | G52: =E52/D52 -> 0.014564967
A53: Deal 52 | B53: =Screening!I53 -> IQTR1759281617 | C53: =Screening!F53 -> 6364.26 | D53: =Screening!L53 -> 1295.67 | E53: =Screening!N53 -> - | F53: =C53/E53 -> #VALUE! | G53: =E53/D53 -> #VALUE!
A54: Deal 53 | B54: =Screening!I54 -> IQTR1903241894 | C54: =Screening!F54 -> 0.25 | D54: =Screening!L54 -> 1283.99 | E54: =Screening!N54 -> 3789 | F54: =C54/E54 -> 6.598047e-05 | G54: =100*(E54/D54) -> 295.09576
A55: Deal 54 | B55: =Screening!I55 -> IQTR1955108370 | C55: =Screening!F55 -> 26153.37 | D55: =Screening!L55 -> 1200.12 | E55: =Screening!N55 -> -2.9 | F55: =C55/E55 -> -9018.4034 | G55: =100*(E55/D55) -> -0.2416425
A56: Deal 55 | B56: =Screening!I56 -> IQTR1888394514 | C56: =Screening!F56 -> 654.83 | D56: =Screening!L56 -> 1146.93 | E56: =Screening!N56 -> - | F56: =C56/E56 -> #VALUE! | G56: =E56/D56 -> #VALUE!
A57: Deal 56 | B57: =Screening!I57 -> IQTR1903107882 | C57: =Screening!F57 -> 7350.58 | D57: =Screening!L57 -> 1140.44 | E57: =Screening!N57 -> 437.4 | F57: =C57/E57 -> 16.805167 | G57: =100*(E57/D57) -> 38.353618
A58: Deal 57 | B58: =Screening!I58 -> IQTR1973474553 | C58: =Screening!F58 -> 12753.02 | D58: =Screening!L58 -> 1113.15 | E58: =Screening!N58 -> -338 | F58: =C58/E58 -> -37.730828 | G58: =100*(E58/D58) -> -30.364282
A59: Deal 58 | B59: =Screening!I59 -> IQTR1880889937 | C59: =Screening!F59 -> 7628.31 | D59: =Screening!L59 -> 1105.7 | E59: =Screening!N59 -> - | F59: =C59/E59 -> #VALUE! | G59: =E59/D59 -> #VALUE!
A60: Deal 59 | B60: =Screening!I60 -> IQTR1834779592 | C60: =Screening!F60 -> 2819.49 | D60: =Screening!L60 -> 1074.5 | E60: =Screening!N60 -> - | F60: =C60/E60 -> #VALUE! | G60: =E60/D60 -> #VALUE!
A61: Deal 60 | B61: =Screening!I61 -> IQTR1870160384 | C61: =Screening!F61 -> 172.56 | D61: =Screening!L61 -> 1049.43 | E61: =Screening!N61 -> - | F61: =C61/E61 -> #VALUE! | G61: =E61/D61 -> #VALUE!
A62: Deal 61 | B62: =Screening!I62 -> IQTR1859816481 | C62: =Screening!F62 -> - | D62: =Screening!L62 -> 1049.43 | E62: =Screening!N62 -> - | F62: =C62/E62 -> #VALUE! | G62: =E62/D62 -> #VALUE!
A63: Deal 62 | B63: =Screening!I63 -> IQTR1898365319 | C63: =Screening!F63 -> 7989.56 | D63: =Screening!L63 -> 1042.26 | E63: =Screening!N63 -> -22.2 | F63: =C63/E63 -> -359.89009 | G63: =100*(E63/D63) -> -2.1299868
A64: Deal 63 | B64: =Screening!I64 -> IQTR1890448244 | C64: =Screening!F64 -> 642.04 | D64: =Screening!L64 -> 1032.81 | E64: =Screening!N64 -> - | F64: =C64/E64 -> #VALUE! | G64: =E64/D64 -> #VALUE!
A65: Deal 64 | B65: =Screening!I65 -> IQTR1868785095 | C65: =Screening!F65 -> 188.18 | D65: =Screening!L65 -> 1015.65 | E65: =Screening!N65 -> -13.6 | F65: =C65/E65 -> -13.836765 | G65: =100*(E65/D65) -> -1.339044
A66: Deal 65 | B66: =Screening!I66 -> IQTR1888805094 | C66: =Screening!F66 -> - | D66: =Screening!L66 -> 970.37 | E66: =Screening!N66 -> - | F66: =C66/E66 -> #VALUE! | G66: =E66/D66 -> #VALUE!
A67: Deal 66 | B67: =Screening!I67 -> IQTR1685197722 | C67: =Screening!F67 -> 336.88 | D67: =Screening!L67 -> 952.34 | E67: =Screening!N67 -> - | F67: =C67/E67 -> #VALUE! | G67: =E67/D67 -> #VALUE!
A68: Deal 67 | B68: =Screening!I68 -> IQTR1849534437 | C68: =Screening!F68 -> 7054.24 | D68: =Screening!L68 -> 951.8 | E68: =Screening!N68 -> - | F68: =C68/E68 -> #VALUE! | G68: =E68/D68 -> #VALUE!
A69: Deal 68 | B69: =Screening!I69 -> IQTR1865270098 | C69: =Screening!F69 -> 5027.93 | D69: =Screening!L69 -> 920.35 | E69: =Screening!N69 -> - | F69: =C69/E69 -> #VALUE! | G69: =E69/D69 -> #VALUE!
A70: Deal 69 | B70: =Screening!I70 -> IQTR1763140911 | C70: =Screening!F70 -> 880.47 | D70: =Screening!L70 -> 909.81 | E70: =Screening!N70 -> - | F70: =C70/E70 -> #VALUE! | G70: =E70/D70 -> #VALUE!
A71: Deal 70 | B71: =Screening!I71 -> IQTR1880250753 | C71: =Screening!F71 -> 2877.57 | D71: =Screening!L71 -> 906.54 | E71: =Screening!N71 -> - | F71: =C71/E71 -> #VALUE! | G71: =E71/D71 -> #VALUE!
A72: Deal 71 | B72: =Screening!I72 -> IQTR1958114138 | C72: =Screening!F72 -> 2233.83 | D72: =Screening!L72 -> 893.84 | E72: =Screening!N72 -> - | F72: =C72/E72 -> #VALUE! | G72: =E72/D72 -> #VALUE!
A73: Deal 72 | B73: =Screening!I73 -> IQTR1887388288 | C73: =Screening!F73 -> - | D73: =Screening!L73 -> 874.25 | E73: =Screening!N73 -> 390.5 | F73: =C73/E73 -> #VALUE! | G73: =E73/D73 -> 0.44666857
A74: Deal 73 | B74: =Screening!I74 -> IQTR1886607085 | C74: =Screening!F74 -> 2959.77 | D74: =Screening!L74 -> 863.38 | E74: =Screening!N74 -> - | F74: =C74/E74 -> #VALUE! | G74: =E74/D74 -> #VALUE!
A75: Deal 74 | B75: =Screening!I75 -> IQTR1818367875 | C75: =Screening!F75 -> 9053.72 | D75: =Screening!L75 -> 818.11 | E75: =Screening!N75 -> - | F75: =C75/E75 -> #VALUE! | G75: =E75/D75 -> #VALUE!
A76: Deal 75 | B76: =Screening!I76 -> IQTR1681371335 | C76: =Screening!F76 -> 11761.32 | D76: =Screening!L76 -> 800 | E76: =Screening!N76 -> - | F76: =C76/E76 -> #VALUE! | G76: =E76/D76 -> #VALUE!
A77: Deal 76 | B77: =Screening!I77 -> IQTR1930453238 | C77: =Screening!F77 -> 4678.82 | D77: =Screening!L77 -> 796.9 | E77: =Screening!N77 -> 273.5 | F77: =C77/E77 -> 17.107203 | G77: =100*(E77/D77) -> 34.320492
A78: Deal 77 | B78: =Screening!I78 -> IQTR1795821068 | C78: =Screening!F78 -> 9831.35 | D78: =Screening!L78 -> 789.43 | E78: =Screening!N78 -> - | F78: =C78/E78 -> #VALUE! | G78: =E78/D78 -> #VALUE!
A79: Deal 78 | B79: =Screening!I79 -> IQTR1966885655 | C79: =Screening!F79 -> 296.88 | D79: =Screening!L79 -> 783.55 | E79: =Screening!N79 -> 52.5 | F79: =C79/E79 -> 5.6548571 | G79: =100*(E79/D79) -> 6.7002744
A80: Deal 79 | B80: =Screening!I80 -> IQTR1988620140 | C80: =Screening!F80 -> 139.57 | D80: =Screening!L80 -> 783.55 | E80: =Screening!N80 -> 52.5 | F80: =C80/E80 -> 2.6584762 | G80: =100*(E80/D80) -> 6.7002744
A81: Deal 80 | B81: =Screening!I81 -> IQTR1980096310 | C81: =Screening!F81 -> 275.74 | D81: =Screening!L81 -> 780 | E81: =Screening!N81 -> - | F81: =C81/E81 -> #VALUE! | G81: =E81/D81 -> #VALUE!
A82: Deal 81 | B82: =Screening!I82 -> IQTR1841959978 | C82: =Screening!F82 -> 4484.95 | D82: =Screening!L82 -> 770.83 | E82: =Screening!N82 -> - | F82: =C82/E82 -> #VALUE! | G82: =E82/D82 -> #VALUE!
A83: Deal 82 | B83: =Screening!I83 -> IQTR2000553888 | C83: =Screening!F83 -> 118.3 | D83: =Screening!L83 -> 763.63 | E83: =Screening!N83 -> 91.3 | F83: =C83/E83 -> 1.2957284 | G83: =100*(E83/D83) -> 11.956052
A84: Deal 83 | B84: =Screening!I84 -> IQTR1885559196 | C84: =Screening!F84 -> 831.85 | D84: =Screening!L84 -> 735.63 | E84: =Screening!N84 -> - | F84: =C84/E84 -> #VALUE! | G84: =E84/D84 -> #VALUE!
A85: Deal 84 | B85: =Screening!I85 -> IQTR1684909762 | C85: =Screening!F85 -> 6339.12 | D85: =Screening!L85 -> 730.43 | E85: =Screening!N85 -> - | F85: =C85/E85 -> #VALUE! | G85: =E85/D85 -> #VALUE!
A86: Deal 85 | B86: =Screening!I86 -> IQTR1879103295 | C86: =Screening!F86 -> 2739.56 | D86: =Screening!L86 -> 728.47 | E86: =Screening!N86 -> - | F86: =C86/E86 -> #VALUE! | G86: =E86/D86 -> #VALUE!
A87: Deal 86 | B87: =Screening!I87 -> IQTR1764591672 | C87: =Screening!F87 -> 1083.73 | D87: =Screening!L87 -> 724.85 | E87: =Screening!N87 -> - | F87: =C87/E87 -> #VALUE! | G87: =E87/D87 -> #VALUE!
A88: Deal 87 | B88: =Screening!I88 -> IQTR1844194992 | C88: =Screening!F88 -> - | D88: =Screening!L88 -> 708.04 | E88: =Screening!N88 -> -9.1 | F88: =C88/E88 -> #VALUE! | G88: =E88/D88 -> -0.012852381
A89: Deal 88 | B89: =Screening!I89 -> IQTR1787619875 | C89: =Screening!F89 -> 618.59 | D89: =Screening!L89 -> 701.06 | E89: =Screening!N89 -> -29.4 | F89: =C89/E89 -> -21.040476 | G89: =100*(E89/D89) -> -4.1936496
A90: Deal 89 | B90: =Screening!I90 -> IQTR1967918116 | C90: =Screening!F90 -> 2735.68 | D90: =Screening!L90 -> 690.59 | E90: =Screening!N90 -> 38.3 | F90: =C90/E90 -> 71.427676 | G90: =100*(E90/D90) -> 5.5459824
A91: Deal 90 | B91: =Screening!I91 -> IQTR1995264367 | C91: =Screening!F91 -> 29.26 | D91: =Screening!L91 -> 684.83 | E91: =Screening!N91 -> - | F91: =C91/E91 -> #VALUE! | G91: =E91/D91 -> #VALUE!
A92: Deal 91 | B92: =Screening!I92 -> IQTR1960281017 | C92: =Screening!F92 -> 52.74 | D92: =Screening!L92 -> 683.55 | E92: =Screening!N92 -> 91.3 | F92: =C92/E92 -> 0.57765608 | G92: =100*(E92/D92) -> 13.356741
A93: Deal 92 | B93: =Screening!I93 -> IQTR1852944845 | C93: =Screening!F93 -> - | D93: =Screening!L93 -> 676.57 | E93: =Screening!N93 -> 390.5 | F93: =C93/E93 -> #VALUE! | G93: =E93/D93 -> 0.57717605
A94: Deal 93 | B94: =Screening!I94 -> IQTR1853092713 | C94: =Screening!F94 -> 621.94 | D94: =Screening!L94 -> 672.92 | E94: =Screening!N94 -> - | F94: =C94/E94 -> #VALUE! | G94: =E94/D94 -> #VALUE!
A95: Deal 94 | B95: =Screening!I95 -> IQTR1791060882 | C95: =Screening!F95 -> 4740.32 | D95: =Screening!L95 -> 671.17 | E95: =Screening!N95 -> - | F95: =C95/E95 -> #VALUE! | G95: =E95/D95 -> #VALUE!
A96: Deal 95 | B96: =Screening!I96 -> IQTR1968615496 | C96: =Screening!F96 -> 31.22 | D96: =Screening!L96 -> 671.05 | E96: =Screening!N96 -> 946.5 | F96: =C96/E96 -> 0.03298468 | G96: =100*(E96/D96) -> 141.04761
A97: Deal 96 | B97: =Screening!I97 -> IQTR1913479166 | C97: =Screening!F97 -> 1254.54 | D97: =Screening!L97 -> 662.29 | E97: =Screening!N97 -> 81.9 | F97: =C97/E97 -> 15.317949 | G97: =100*(E97/D97) -> 12.366184
A98: Deal 97 | B98: =Screening!I98 -> IQTR1879230826 | C98: =Screening!F98 -> 5591.6 | D98: =Screening!L98 -> 653.95 | E98: =Screening!N98 -> - | F98: =C98/E98 -> #VALUE! | G98: =E98/D98 -> #VALUE!
A99: Deal 98 | B99: =Screening!I99 -> IQTR1902476016 | C99: =Screening!F99 -> 10700.92 | D99: =Screening!L99 -> 644.66 | E99: =Screening!N99 -> 60.3 | F99: =C99/E99 -> 177.46136 | G99: =100*(E99/D99) -> 9.3537679
A100: Deal 99 | B100: =Screening!I100 -> IQTR1777910955 | C100: =Screening!F100 -> 6219.6 | D100: =Screening!L100 -> 644.53 | E100: =Screening!N100 -> - | F100: =C100/E100 -> #VALUE! | G100: =E100/D100 -> #VALUE!
...

Sheet BENCHMARKS
B1: Revenue LTM | C1: EBITDA LTM | D1: Entry Multiple | E1: EBITDA Margin | G1: Count | H1: # | I1: Deal ID | J1: Deal Value | K1: Revenue LTM | L1: EBITDA LTM | M1: Entry Multiple | N1: EBITDA Margin
A2: Median | B2: =MEDIAN(K2:K26) -> 288.9 | C2: =MEDIAN(L2:L26) -> 45.4 | D2: =MEDIAN(M2:M26) -> 10.533333 | E2: =MEDIAN(N2:N26) -> 17.029725 | G2: 1 | H2: Deal 8 | I2: IQTR1967911118 | J2: 4359.34 | K2: 4836.99 | L2: 766.3 | M2: 5.6888164 | N2: 15.842497
A3: Mean | B3: =AVERAGE(K2:K26) -> 593.3944 | C3: =AVERAGE(L2:L26) -> 131.9452 | D3: =AVERAGE(M2:M26) -> 10.274033 | E3: =AVERAGE(N2:N26) -> 21.434774 | G3: 2 | H3: Deal 44 | I3: IQTR1903250285 | J3: 1967.76 | K3: 1484.46 | L3: 167 | M3: 11.782994 | N3: 11.249882
A4: 25th percentile | B4: =QUARTILE(K2:K26,1) -> 88.23 | C4: =QUARTILE(L2:L26,1) -> 29.3 | D4: =QUARTILE(M2:M26,1) -> 6.7617433 | E4: =QUARTILE(N2:N26,1) -> 13.016453 | G4: 3 | H4: Deal 49 | I4: IQTR1781913531 | J4: 7543.48 | K4: 1386.92 | L4: 750.3 | M4: 10.053952 | N4: 54.09829
A5: 75th percentile | B5: =QUARTILE(K2:K26,3) -> 552.52 | C5: =QUARTILE(L2:L26,3) -> 93.5 | D5: =QUARTILE(M2:M26,3) -> 13.549267 | E5: =QUARTILE(N2:N26,3) -> 27.706844 | G5: 4 | H5: Deal 56 | I5: IQTR1903107882 | J5: 7350.58 | K5: 1140.44 | L5: 437.4 | M5: 16.805167 | N5: 38.353618
A6: Min | B6: =MIN(K2:K26) -> 54.7 | C6: =MIN(L2:L26) -> 7.12 | D6: =MIN(M2:M26) -> 4.4775281 | E6: =MIN(N2:N26) -> 10.00834 | G6: 5 | H6: Deal 76 | I6: IQTR1930453238 | J6: 4678.82 | K6: 796.9 | L6: 273.5 | M6: 17.107203 | N6: 34.320492
A7: Max | B7: =MAX(K2:K26) -> 4836.99 | C7: =MAX(L2:L26) -> 766.3 | D7: =MAX(M2:M26) -> 17.107203 | E7: =MAX(N2:N26) -> 54.09829 | G7: 6 | H7: Deal 96 | I7: IQTR1913479166 | J7: 1254.54 | K7: 662.29 | L7: 81.9 | M7: 15.317949 | N7: 12.366184
A8: Count | B8: =COUNT(K2:K26) -> 25 | C8: =COUNT(L2:L26) -> 25 | D8: =COUNT(M2:M26) -> 25 | E8: =COUNT(N2:N26) -> 25 | G8: 7 | H8: Deal 120 | I8: IQTR1934842365 | J8: 808.96 | K8: 552.52 | L8: 76.8 | M8: 10.533333 | N8: 13.899949
G9: 8 | H9: Deal 121 | I9: IQTR1956594929 | J9: 1434.05 | K9: 549.04 | L9: 93.5 | M9: 15.337433 | N9: 17.029725
G10: 9 | H10: Deal 129 | I10: IQTR1848494184 | J10: 310.25 | K10: 482.88 | L10: 54.6 | M10: 5.6822344 | N10: 11.307157
G11: 10 | H11: Deal 135 | I11: IQTR1848560033 | J11: 739.79 | K11: 463.96 | L11: 54.6 | M11: 13.549267 | N11: 11.768256
G12: 11 | H12: Deal 161 | I12: IQTR1889524439 | J12: 522.1 | K12: 345.14 | L12: 45.4 | M12: 11.5 | N12: 13.154082
G13: 12 | H13: Deal 181 | I13: IQTR1969539143 | J13: 900.9 | K13: 306.53 | L13: 125.7 | M13: 7.1670644 | N13: 41.007405
G14: 13 | H14: Deal 189 | I14: IQTR1913989358 | J14: 444.57 | K14: 288.9 | L14: 83.5 | M14: 5.3241916 | N14: 28.902735
G15: 14 | H15: Deal 197 | I15: IQTR1962910014 | J15: 319.98 | K15: 273.57 | L15: 35.7 | M15: 8.9630252 | N15: 13.049676
G16: 15 | H16: Deal 225 | I16: IQTR1914744113 | J16: 279.26 | K16: 225.74 | L16: 41.3 | M16: 6.7617433 | N16: 18.295384
G17: 16 | H17: Deal 257 | I17: IQTR1815364960 | J17: 184.55 | K17: 192.01 | L17: 40.5 | M17: 4.5567901 | N17: 21.092651
G18: 17 | H18: Deal 283 | I18: IQTR1973020838 | J18: 297.14 | K18: 170.91 | L18: 32.6 | M18: 9.1147239 | N18: 19.074367
G19: 18 | H19: Deal 323 | I19: IQTR2000108346 | J19: 440.08 | K19: 139.54 | L19: 29.3 | M19: 15.019795 | N19: 20.997563
G20: 19 | H20: Deal 414 | I20: IQTR1930066296 | J20: 139.46 | K20: 88.23 | L20: 12.2 | M20: 11.431148 | N20: 13.827496
... G26: 25 | H26: Deal 525 | I26: IQTR1963039166 | J26: 31.88 | K26: 54.7 | L26: 7.12 | M26: 4.4775281 | N26: 13.016453

Sheet Screening
A1: All Transactions Announced Date | B1: Target/Issuer | C1: Exchange:Ticker | D1: Transaction Types | E1: Transaction Status | F1: Total Transaction Value ($USDmm, Historical rate) | G1: Buyers/Investors | H1: Sellers | I1: CIQ Transaction ID | J1: M&A Announced Date | K1: Industry Classifications [Target/Issuer] | L1: Target/Issuer LTM Financials - Total Revenue (at Announcement) ($USDmm, Historical rate) | M1: M&A Closed Date | N1: EBITDA [LTM] ($USDmm, Historical rate) [Target/Issuer] | O1: Merger/Acquisition Features
A2: 2025-05-08 | B2: NTT DATA Group Corporation | C2: - | D2: Merger/Acquisition | E2: Closed | F2: 9243.42 | G2: - | H2: - | I2: IQTR1942758117 | J2: 2025-05-08 | K2: Software and Services (Primary) | L2: 30976.85 | M2: 2025-06-19 | N2: 5335.2 | O2: Acquisition of Minority Stake; Cash Merger; Going Private Transaction; Majority Shareholder Increasing Ownership Stake; Majority Shareholder Purchasing Remaining Shares; Squeeze Out / Short Form Merger; Tender Offer; Tender Offer (Full Bid)
A3: 2022-05-26 | B3: VMware LLC | C3: - | D3: Merger/Acquisition | E3: Closed | F3: 72967.49 | G3: Broadcom Inc. (NasdaqGS:AVGO) | H3: Silver Lake Technology Management, L.L.C.; Dodge & Cox; Silver Lake Partners V DE (AIV), L.P. | I3: IQTR1784746799 | J3: 2022-05-26 | K3: Software and Services (Primary) | L3: 12945 | M3: 2023-11-22 | N3: - | O3: Acquisition of Majority Stake; Go Shop Provision
A4: 2023-11-02 | B4: Atos Group (ENXTPA:ATO) | C4: ENXTPA:ATO | D4: Merger/Acquisition | E4: Closed | F4: - | G4: Onepoint SAS | H4: - | I4: IQTR1860930383 | J4: 2023-11-02 | K4: Software and Services (Primary) | L4: 11615.16 | M4: 2023-11-02 | N4: 534.7 | O4: Acquisition of Minority Stake; Terms Not Disclosed
A5: 2025-05-19 | B5: DataCenter Infrastructure Manufacturing Business of ZT Group Intl, Inc. | C5: - | D5: Merger/Acquisition | E5: Closed | F5: 3000 | G5: Sanmina Corporation (NasdaqGS:SANM) | H5: ZT Group Intl, Inc. | I5: IQTR1944075963 | J5: 2025-05-19 | K5: Software and Services (Primary) | L5: 6000 | M5: 2025-10-27 | N5: - | O5: Acquisition of Majority Stake; Corporate Divestiture; Earnout Payments
A6: 2024-01-09 | B6: Juniper Networks, Inc. | C6: - | D6: Merger/Acquisition | E6: Closed | F6: 15396.69 | G6: Hewlett Packard Enterprise Company (NYSE:HPE) | H6: - | I6: IQTR1867916120 | J6: 2024-01-09 | K6: Software and Services (Primary) | L6: 5564.5 | M6: 2025-07-02 | N6: 689.8 | O6: Acquisition of Majority Stake; Cash Merger
A7: 2024-12-05 | B7: Indra Sistemas, S.A. (BME:IDR) | C7: BME:IDR | D7: Merger/Acquisition | E7: Closed | F7: - | G7: Escribano Mechanical And Engineering, S.L. | H7: - | I7: IQTR1912024769 | J7: 2024-12-05 | K7: Software and Services (Primary) | L7: 5330.6 | M7: 2024-12-05 | N7: 776.9 | O7: Acquisition of Minority Stake; Minority Shareholder Increasing Ownership Stake; Terms Not Disclosed
A8: 2022-03-23 | B8: Nomura Research Institute, Ltd. (TSE:4307) | C8: TSE:4307 | D8: Merger/Acquisition | E8: Closed | F8: 478.06 | G8: - | H8: Nomura Holdings, Inc. (TSE:8604) | I8: IQTR1776383559 | J8: 2022-03-23 | K8: Software and Services (Primary) | L8: 5157.45 | M8: 2022-03-23 | N8: 698.6 | O8: Acquisition of Minority Stake
A9: 2025-10-29 | B9: SCSK Corporation | C9: - | D9: Merger/Acquisition | E9: Closed | F9: 4359.34 | G9: Sumitomo Corporation (TSE:8053) | H9: ARGO GRAPHICS Inc. (TSE:7595); State Street Bank & Trust Company 505001; State Street Bank and Trust Company 510312; Government Of Norway; State Street Bank West Client - Treaty 505234; Custody Bank of Japan, Ltd. (Trust Account); The Master Trust Bank of Japan, Ltd. (Trust Account); Custody Bank of Japan, Ltd. (Trust Account 4) | I9: IQTR1967911118 | J9: 2025-10-29 | K9: Software and Services (Primary) | L9: 4836.99 | M9: 2025-12-12 | N9: 766.3 | O9: Acquisition of Minority Stake; Majority Shareholder Increasing Ownership Stake; Tender Offer; Tender Offer (Full Bid)
A10: 2025-08-04 | B10: iSoftStone Information Technology (Group) Co., Ltd. (SZSE:301236) | C10: SZSE:301236 | D10: Merger/Acquisition | E10: Closed | F10: 141.01 | G10: UBS Group AG (SWX:UBSG); Morgan Stanley & Co. International plc; Guotai Haitong Securities Co., Ltd. (SHSE:601211); J.P. Morgan Securities plc; GF Securities Co., Ltd. (SZSE:000776); Sealand Securities Co., Ltd. (SZSE:000750); China Asset Management Co. Ltd.; E Fund Management Co., Ltd.; Nuode Asset Management Co., Ltd.; Caitong Fund Management Co., Ltd.; Dajia Asset Management Co., Ltd.; Zhong Ou Fund Management Co., Ltd; Shanghai Muxin Private Fund Management Co., Ltd.; Yingshui Investment Co., Ltd.; Shenzhen Commando Capital Management Co., Ltd.; Hangzhou Lexin Investment Management Co., Ltd.; Hunan Chasing Asset Management Co.,Ltd.; Nanjing Shengquan Hengyuan Investment Co., Ltd.; Ningbo Meishan Bonded Port Lingding Investment Management Co., Ltd.; Qingdao Luxiu Investment Management Co., Ltd.; Shanghai Qinsheng Private Fund Management Co., Ltd.; Zhijian (Shaoxing Keqiao) Private Equity Fund Management Co., Ltd.; Beijing Pingfan Private Equity Fund Management Co., Ltd.; Huaan Securities Asset Management Co., Ltd.; Chengdu Fuende Tongchuang Asset Management Co., Ltd; Shanghai Dunyuan Private Equity Fund Management Co., Ltd; Beijing Yuexi Private Fund Management Co., Ltd; Xiamen Fengqiaolin Private Fund Management Co., Ltd | H10: FNOF Easynet (HK) Limited | I10: IQTR1955725309 | J10: 2025-08-04 | K10: Software and Services (Primary) | L10: 4825.83 | M10: 2025-08-04 | N10: 10.6 | O10: Acquisition of Minority Stake; Cross-Border
A11: 2023-11-30 | B11: Indra Sistemas, S.A. (BME:IDR) | C11: BME:IDR | D11: Merger/Acquisition | E11: Closed | F11: - | G11: JPMorgan Chase & Co. (NYSE:JPM) | H11: - | I11: IQTR1863840995 | J11: 2023-11-30 | K11: Software and Services (Primary) | L11: 4475 | M11: 2023-11-30 | N11: 776.9 | O11: Acquisition of Minority Stake; Cross-Border
A12: 2023-11-24 | B12: Indra Sistemas, S.A. (BME:IDR) | C12: BME:IDR | D12: Merger/Acquisition | E12: Closed | F12: 129.05 | G12: Escribano Mechanical And Engineering, S.L. | H12: JPMorgan Chase & Co. (NYSE:JPM) | I12: IQTR1862954563 | J12: 2023-11-24 | K12: Software and Services (Primary) | L12: 4475 | M12: 2023-11-24 | N12: 776.9 | O12: Acquisition of Minority Stake; Minority Shareholder Increasing Ownership Stake
A13: 2023-05-15 | B13: Indra Sistemas, S.A. (BME:IDR) | C13: BME:IDR | D13: Merger/Acquisition | E13: Closed | F13: 70.67 | G13: Escribano Mechanical And Engineering, S.L. | H13: - | I13: IQTR1838306852 | J13: 2023-05-15 | K13: Software and Services (Primary) | L13: 4301.36 | M13: 2023-05-15 | N13: 776.9 | O13: Acquisition of Minority Stake
A14: 2025-01-31 | B14: Asseco Poland S.A. (WSE:ACP) | C14: WSE:ACP | D14: Merger/Acquisition | E14: Closed | F14: 174 | G14: Yukon Niebieski Kapital B.V. | H14: Cyfrowy Polsat S.A. (WSE:CPS) | I14: IQTR1929482728 | J14: 2025-01-31 | K14: Software and Services (Primary) | L14: 4145.17 | M14: 2025-01-31 | N14: 668.9 | O14: Acquisition of Minority Stake; Cross-Border
A15: 2023-08-02 | B15: ITOCHU Techno-Solutions Corporation | C15: - | D15: Merger/Acquisition | E15: Closed | F15: 1678.11 | G15: ITOCHU Corporation (TSE:8001) | H15: - | I15: IQTR1850957260 | J15: 2023-08-02 | K15: Software and Services (Primary) | L15: 4057.13 | M15: 2023-09-14 | N15: - | O15: Acquisition of Minority Stake; Majority Shareholder Increasing Ownership Stake; Tender Offer; Tender Offer (Full Bid)
A16: 2022-06-03 | B16: Indra Sistemas, S.A. (BME:IDR) | C16: BME:IDR | D16: Merger/Acquisition | E16: Closed | F16: 66.77 | G16: SAPA Placencia Holding, S.L. | H16: Corporación Financiera Alba, S.A. | I16: IQTR1785931677 | J16: 2022-06-03 | K16: Software and Services (Primary) | L16: 3926.97 | M16: 2022-06-03 | N16: 776.9 | O16: Acquisition of Minority Stake
A17: 2023-09-21 | B17: Splunk Inc. | C17: - | D17: Merger/Acquisition | E17: Closed | F17: 30998.87 | G17: Cisco Systems, Inc. (NasdaqGS:CSCO) | H17: Hellman & Friedman LLC; Silver Lake Technology Management, L.L.C.; BlackRock, Inc. (NYSE:BLK); The Vanguard Group, Inc.; PRIMECAP Management Company | I17: IQTR1856318900 | J17: 2023-09-21 | K17: Software and Services (Primary) | L17: 3842.97 | M17: 2024-03-18 | N17: - | O17: Acquisition of Majority Stake; Cash Merger
A18: 2021-12-14 | B18: Indra Sistemas, S.A. (BME:IDR) | C18: BME:IDR | D18: Merger/Acquisition | E18: Closed | F18: 102.35 | G18: SAPA Placencia Holding, S.L. | H18: Corporación Financiera Alba, S.A. | I18: IQTR1762042686 | J18: 2021-12-14 | K18: Software and Services (Primary) | L18: 3841.83 | M18: 2021-12-14 | N18: 776.9 | O18: Acquisition of Minority Stake
A19: 2022-11-23 | B19: Indra Sistemas, S.A. (BME:IDR) | C19: BME:IDR | D19: Merger/Acquisition | E19: Closed | F19: 45.4 | G19: Goldman Sachs (Singapore) Pte | H19: - | I19: IQTR1816233358 | J19: 2022-11-23 | K19: Software and Services (Primary) | L19: 3694.6 | M19: 2022-11-23 | N19: 776.9 | O19: Acquisition of Minority Stake; Cross-Border; Minority Shareholder Increasing Ownership Stake
A20: 2021-09-08 | B20: Tieto Oyj (HLSE:TIETO) | C20: HLSE:TIETO | D20: Merger/Acquisition | E20: Closed | F20: - | G20: - | H20: - | I20: IQTR1680643570 | J20: 2021-09-08 | K20: Software and Services (Primary) | L20: 3311.12 | M20: 2021-09-08 | N20: 396 | O20: Acquisition of Minority Stake; Terms Not Disclosed
A21: 2022-01-31 | B21: Citrix Systems, Inc. | C21: - | D21: Merger/Acquisition | E21: Closed | F21: 17182.11 | G21: Cloud Software Group, Inc. | H21: BlackRock, Inc. (NYSE:BLK); The Vanguard Group, Inc.; Elliott Management Corporation; T. Rowe Price Associates, Inc. | I21: IQTR1765987121 | J21: 2022-01-31 | K21: Software and Services (Primary) | L21: 3217.17 | M21: 2022-09-30 | N21: - | O21: Acquisition of Majority Stake; Cash Merger; Going Private Transaction; Leveraged Buy Out (LBO)
A22: 2023-08-25 | B22: Tieto Oyj (HLSE:TIETO) | C22: HLSE:TIETO | D22: Merger/Acquisition | E22: Closed | F22: - | G22: Silchester International Investors LLP | H22: - | I22: IQTR1853829677 | J22: 2023-08-25 | K22: Software and Services (Primary) | L22: 3164.63 | M22: 2023-08-24 | N22: 396 | O22: Acquisition of Minority Stake; Cross-Border; Minority Shareholder Increasing Ownership Stake; Terms Not Disclosed
A23: 2022-08-25 | B23: Micro Focus International Limited | C23: - | D23: Merger/Acquisition | E23: Closed | F23: 6477.38 | G23: Open Text Corporation (NasdaqGS:OTEX) | H23: Dodge & Cox | I23: IQTR1798157276 | J23: 2022-08-25 | K23: Software and Services (Primary) | L23: 2743.8 | M23: 2023-01-31 | N23: - | O23: Acquisition of Majority Stake; Cash Merger; Cross-Border
A24: 2023-01-11 | B24: Sinch AB (publ) (OM:SINCH) | C24: OM:SINCH | D24: Merger/Acquisition | E24: Closed | F24: - | G24: Swedbank Robur Fonder AB | H24: - | I24: IQTR1821576629 | J24: 2023-01-11 | K24: Software and Services (Primary) | L24: 2659.43 | M24: 2022-12-31 | N24: 282.7 | O24: Acquisition of Minority Stake; Terms Not Disclosed
A25: 2024-01-16 | B25: ANSYS, Inc. | C25: - | D25: Merger/Acquisition | E25: Closed | F25: 35791.48 | G25: Synopsys, Inc. (NasdaqGS:SNPS) | H25: BlackRock, Inc. (NYSE:BLK); The Vanguard Group, Inc. | I25: IQTR1868555623 | J25: 2024-01-16 | K25: Software and Services (Primary) | L25: 2583.1 | M25: 2025-07-17 | N25: 878 | O25: Acquisition of Majority Stake
A26: 2024-10-29 | B26: NEC Networks & System Integration Corporation | C26: - | D26: Merger/Acquisition | E26: Closed | F26: 702 | G26: NEC Corporation (TSE:6701) | H26: Sumitomo Realty & Development Co., Ltd. (TSE:8830); The Master Trust Bank of Japan, Ltd.; Norway; State Street Bank and Trust Company 510312; BNY GCM CLIENT ACCOUNT JPRD AC ISG (FE-AC); JP Morgan Chase Bank 385632; Custody Bank of Japan, Ltd. (Trust Account); Employees’ Stock Ownership Plan of NEC Networks & System | I26: IQTR1902207620 | J26: 2024-10-29 | K26: Software and Services (Primary) | L26: 2390.56 | M26: 2025-01-10 | N26: 209 | O26: Acquisition of Minority Stake; Majority Shareholder Increasing Ownership Stake; Tender Offer; Tender Offer (Partial Bid)
A27: 2021-09-09 | B27: Visma AS | C27: - | D27: Merger/Acquisition | E27: Closed | F27: - | G27: GIC Private Limited; Folketrygdfondet; Aeternum Management AS; Vind Group | H27: - | I27: IQTR1681724164 | J27: 2021-09-09 | K27: Software and Services (Primary) | L27: 2377.81 | M27: 2021-09-09 | N27: 759.9 | O27: Acquisition of Minority Stake; Cross-Border; Terms Not Disclosed
A28: 2024-08-08 | B28: Fuji Soft Incorporated | C28: - | D28: Merger/Acquisition | E28: Closed | F28: 1239.77 | G28: KKR & Co. Inc. (NYSE:KKR) | H28: Farallon Capital Management, L.L.C.; Custody Bank of Japan, Ltd.; The Master Trust Bank of Japan, Ltd.; State Street Bank And Trust Company; Yugen Kaisha NFC; 3D Investment Partners Pte. Ltd; Goldman Sachs & Co. REG; Cabrillo Funding Ltd. | I28: IQTR1890818396 | J28: 2024-08-08 | K28: Software and Services (Primary) | L28: 2178.56 | M28: 2024-11-05 | N28: 184.6 | O28: Acquisition of Minority Stake; Cross-Border; Tender Offer; Tender Offer (Full Bid)
A29: 2022-09-29 | B29: Sinch AB (publ) (OM:SINCH) | C29: OM:SINCH | D29: Merger/Acquisition | E29: Closed | F29: - | G29: Neqst D2 AB | H29: SoftBank Corp. (TSE:9434) | I29: IQTR1802771200 | J29: 2022-09-29 | K29: Software and Services (Primary) | L29: 2177.1 | M29: 2022-09-29 | N29: 282.7 | O29: Acquisition of Minority Stake; Management Participated; Minority Shareholder Increasing Ownership Stake; Terms Not Disclosed
A30: 2021-10-18 | B30: Sirius Computer Solutions, LLC. | C30: - | D30: Merger/Acquisition | E30: Closed | F30: 2500 | G30: CDW LLC | H30: Clayton, Dubilier & Rice, LLC | I30: IQTR1685463254 | J30: 2021-10-18 | K30: Software and Services (Primary) | L30: 2035 | M30: 2021-12-01 | N30: - | O30: Acquisition of Majority Stake; Cash Merger
A31: 2024-11-15 | B31: Fuji Soft Incorporated | C31: - | D31: Merger/Acquisition | E31: Closed | F31: 2987.11 | G31: KKR & Co. Inc. (NYSE:KKR) | H31: Custody Bank of Japan, Ltd.; Tokyo Century Corporation (TSE:8439); The Master Trust Bank of Japan, Ltd.; State Street Bank And Trust Company; Yugen Kaisha NFC; The Hongkong And Shanghai Banking Corp. Ltd. Tokyo Branch; Goldman Sachs & Co. REG; Cabrillo Funding Ltd. | I31: IQTR1904331229 | J31: 2024-11-15 | K31: Software and Services (Primary) | L31: 2019.35 | M31: 2025-02-19 | N31: 184.6 | O31: Acquisition of Majority Stake; Cash Merger; Cross-Border; Going Private Transaction; Leveraged Buy Out (LBO); Minority Shareholder Increasing Ownership Stake; Minority Shareholder Purchasing Remaining Shares; Squeeze Out / Short Form Merger; Tender Offer; Tender Offer (Full Bid)
A32: 2022-03-07 | B32: vCORE Technology Partners, LLC | C32: - | D32: Merger/Acquisition | E32: Closed | F32: - | G32: AHEAD, Inc. | H32: - | I32: IQTR1773626089 | J32: 2022-03-07 | K32: Software and Services (Primary) | L32: 2000 | M32: 2022-03-07 | N32: - | O32: Acquisition of Majority Stake; Terms Not Disclosed
A33: 2021-11-08 | B33: McAfee Corp. | C33: - | D33: Merger/Acquisition | E33: Closed | F33: 20862.21 | G33: Advent International, L.P.; Permira Advisers Ltd.; GIC Private Limited; Canada Pension Plan Investment Board; Abu Dhabi Investment Authority; Crosspoint Capital Partners, LP | H33: McAfee, LLC; TPG Global, LLC; TPG VII Manta AIV Co-Invest, L.P.; TPG VII Manta Blocker Co-Invest I, L.P.; TPG VII Manta AIV I, L.P.; TPG VII Manta Holdings II, L.P.; TPG VII Side-by-Side Separate Account I, L.P. | I33: IQTR1757348954 | J33: 2021-11-08 | K33: Software and Services (Primary) | L33: 1826 | M33: 2022-03-01 | N33: - | O33: Acquisition of Majority Stake; Cash Merger; Cross-Border; Go Shop Provision; Going Private Transaction
A34: 2025-02-07 | B34: Converge Technology Solutions Corp. | C34: - | D34: Merger/Acquisition | E34: Closed | F34: 1010.8 | G34: Mainline Information Systems, LLC | H34: Mawer Investment Management Ltd.; Mcmillan Family Foundation; 2491626 Ontario Inc.; Acoma Investments Limited | I34: IQTR1930420741 | J34: 2025-02-07 | K34: Software and Services (Primary) | L34: 1801.51 | M34: 2025-04-22 | N34: 100.2 | O34: Acquisition of Majority Stake; Cash Merger; Consolidation/Roll Up; Cross-Border; Going Private Transaction
A35: 2022-02-24 | B35: AKKA Technologies SE | C35: - | D35: Merger/Acquisition | E35: Closed | F35: 291.2 | G35: Akkodis Group AG | H35: - | I35: IQTR1772509697 | J35: 2022-02-24 | K35: Software and Services (Primary) | L35: 1766.63 | M35: 2022-04-20 | N35: - | O35: Acquisition of Minority Stake; Cross-Border; Majority Shareholder Increasing Ownership Stake; Majority Shareholder Purchasing Remaining Shares; Squeeze Out / Short Form Merger; Tender Offer; Tender Offer (Partial Bid)
A36: 2022-04-07 | B36: CDK Global, LLC | C36: - | D36: Merger/Acquisition | E36: Closed | F36: 8340.71 | G36: Brookfield Business Corporation (TSX:BBUC) | H36: - | I36: IQTR1777417497 | J36: 2022-04-07 | K36: Software and Services (Primary) | L36: 1756.5 | M36: 2022-07-05 | N36: - | O36: Acquisition of Majority Stake; Cash Merger; Cross-Border; Going Private Transaction; Leveraged Buy Out (LBO); Squeeze Out / Short Form Merger; Tender Offer; Tender Offer (Full Bid)
A37: 2022-12-16 | B37: Vantor Parent Inc. | C37: - | D37: Merger/Acquisition | E37: Closed | F37: 6570.02 | G37: Advent International, L.P.; British Columbia Investment Management Corporation | H37: BlackRock, Inc. (NYSE:BLK); The Vanguard Group, Inc. | I37: IQTR1818826920 | J37: 2022-12-16 | K37: Software and Services (Primary) | L37: 1747 | M37: 2023-05-03 | N37: - | O37: Acquisition of Majority Stake; Cash Merger; Cross-Border; Go Shop Provision; Leveraged Buy Out (LBO)
A38: 2021-11-09 | B38: Noventiq Holdings plc | C38: - | D38: Merger/Acquisition | E38: Closed | F38: - | G38: - | H38: Softline Group | I38: IQTR1760525650 | J38: 2021-11-09 | K38: Software and Services (Primary) | L38: 1734.66 | M38: 2021-11-01 | N38: - | O38: Acquisition of Minority Stake
A39: 2025-05-27 | B39: Informatica Inc. | C39: - | D39: Merger/Acquisition | E39: Closed | F39: 10097.75 | G39: Salesforce, Inc. (NYSE:CRM) | H39: Bank of America Corporation (NYSE:BAC); Canada Pension Plan Investment Board; EvomLux S.à r.l.; Ithaca Limited; 13381986 Canada, Inc. | I39: IQTR1945143029 | J39: 2025-05-27 | K39: Software and Services (Primary) | L39: 1655.31 | M39: 2025-11-18 | N39: 280.9 | O39: Acquisition of Majority Stake; Cash Merger
A40: 2024-07-24 | B40: Exclusive Networks SA | C40: - | D40: Merger/Acquisition | E40: Closed | F40: 803.5 | G40: Clayton, Dubilier & Rice, LLC; Permira Advisers Ltd. | H40: - | I40: IQTR1888824933 | J40: 2024-07-24 | K40: Software and Services (Primary) | L40: 1613.63 | M40: 2025-02-28 | N40: - | O40: Acquisition of Minority Stake; Cash Merger; Cross-Border; Going Private Transaction; Majority Shareholder Increasing Ownership Stake; Squeeze Out / Short Form Merger; Tender Offer; Tender Offer (Full Bid)
A41: 2024-07-09 | B41: Exclusive Networks SA | C41: - | D41: Merger/Acquisition | E41: Closed | F41: 2217.86 | G41: Clayton, Dubilier & Rice, LLC; Permira Advisers Ltd. | H41: Permira Advisers Ltd. | I41: IQTR1887815986 | J41: 2024-07-09 | K41: Software and Services (Primary) | L41: 1613.63 | M41: 2024-12-17 | N41: - | O41: Acquisition of Majority Stake; Cross-Border; Equity Reinvestment; Leveraged Buy Out (LBO)
A42: 2022-05-04 | B42: Black Knight, Inc. | C42: - | D42: Merger/Acquisition | E42: Closed | F42: 14772.33 | G42: Intercontinental Exchange, Inc. (NYSE:ICE) | H42: - | I42: IQTR1781572984 | J42: 2022-05-04 | K42: Software and Services (Primary) | L42: 1551.9 | M42: 2023-09-05 | N42: - | O42: Acquisition of Majority Stake
A43: 2022-03-21 | B43: Kontron AG (XTRA:KTN) | C43: XTRA:KTN | D43: Merger/Acquisition | E43: Closed | F43: 92.94 | G43: Grosso Tec AG | H43: - | I43: IQTR1775144551 | J43: 2022-03-21 | K43: Software and Services (Primary) | L43: 1526.16 | M43: 2022-04-13 | N43: 131.4 | O43: Acquisition of Minority Stake; Cross-Border; Tender Offer; Tender Offer (Partial Bid)
A44: 2026-05-13 | B44: VNET Group, Inc. (NasdaqGS:VNET) | C44: NasdaqGS:VNET | D44: Merger/Acquisition | E44: Closed | F44: 942.2 | G44: PJ Millennium Limited Partnership | H44: Shandong Hi-Speed Holdings Group Limited (SEHK:412) | I44: IQTR2000373976 | J44: 2026-05-13 | K44: Software and Services (Primary) | L44: 1506.97 | M44: 2026-08-24 | N44: 483.1 | O44: Acquisition of Minority Stake
A45: 2024-11-06 | B45: Net One Systems Co., Ltd. | C45: - | D45: Merger/Acquisition | E45: Closed | F45: 1967.76 | G45: SCSK Corporation | H45: Meiji Yasuda Life Insurance Company; Taiyo Pacific Partners L.P.; Custody Bank of Japan, Ltd.; The Master Trust Bank of Japan, Ltd.; State Street Bank & Trust Company 505001; State Street Bank And Trust Company 505227; The Bank of New York Mellon 140044; CGML PB CLIENT ACCOUNT/COLLATERAL; JP Morgan Chase Bank 385781; Government Of Norway; State Street Bank West Client - Treaty 505234; NORTHERN TRUST CO. (AVFC) RE FIDELITY FUNDS | I45: IQTR1903250285 | J45: 2024-11-06 | K45: Software and Services (Primary) | L45: 1484.46 | M45: 2024-12-18 | N45: 167 | O45: Acquisition of Majority Stake; Tender Offer; Tender Offer (Full Bid)
A46: 2023-03-12 | B46: Qualtrics International Inc. | C46: - | D46: Merger/Acquisition | E46: Closed | F46: 11166.16 | G46: Silver Lake Technology Management, L.L.C.; Canada Pension Plan Investment Board | H46: The Vanguard Group, Inc.; SAP America, Inc. | I46: IQTR1829326219 | J46: 2023-03-12 | K46: Software and Services (Primary) | L46: 1458.63 | M46: 2023-06-28 | N46: - | O46: Acquisition of Majority Stake; Cash Merger; Cross-Border; Going Private Transaction; Minority Shareholder Increasing Ownership Stake
A47: 2022-06-24 | B47: Zendesk, Inc. | C47: - | D47: Merger/Acquisition | E47: Closed | F47: 10989.54 | G47: Hellman & Friedman LLC; Permira Advisers Ltd.; GIC Private Limited; Abu Dhabi Investment Authority | H47: BlackRock, Inc. (NYSE:BLK); The Vanguard Group, Inc.; Capital World Investors; Light Street Capital Management, LLC | I47: IQTR1788006790 | J47: 2022-06-24 | K47: Software and Services (Primary) | L47: 1428.88 | M47: 2022-11-22 | N47: - | O47: Acquisition of Majority Stake; Cash Merger; Cross-Border; Going Private Transaction
A48: 2026-02-02 | B48: Systex Corporation (TWSE:6214) | C48: TWSE:6214 | D48: Merger/Acquisition | E48: Closed | F48: - | G48: ITOCHU Corporation (TSE:8001) | H48: - | I48: IQTR1981910022 | J48: 2026-02-02 | K48: Software and Services (Primary) | L48: 1400.21 | M48: 2026-02-02 | N48: 66.3 | O48: Acquisition of Minority Stake; Cross-Border; Terms Not Disclosed
A49: 2022-09-21 | B49: AVEVA Group Limited | C49: - | D49: Merger/Acquisition | E49: Closed | F49: 4683.21 | G49: Schneider Electric S.E. (ENXTPA:SU) | H49: - | I49: IQTR1801227134 | J49: 2022-09-21 | K49: Software and Services (Primary) | L49: 1399.44 | M49: 2023-01-18 | N49: - | O49: Acquisition of Minority Stake; Cross-Border
A50: 2022-05-06 | B50: Mindtree Limited | C50: - | D50: Merger/Acquisition | E50: Closed | F50: 7543.48 | G50: LTM Limited (NSEI:LTM) | H50: - | I50: IQTR1781913531 | J50: 2022-05-06 | K50: Software and Services (Primary) | L50: 1386.92 | M50: 2022-11-14 | N50: 750.3 | O50: Acquisition of Majority Stake; Stock Merger
A51: 2024-07-11 | B51: Envestnet, Inc. | C51: - | D51: Merger/Acquisition | E51: Closed | F51: 4407.65 | G51: Franklin Templeton Inc. (NYSE:BEN); BlackRock, Inc. (NYSE:BLK); State Street Investment Management; Bain Capital Private Equity, LP; Reverence Capital Partners, L.P.; FMR LLC | H51: BlackRock, Inc. (NYSE:BLK); The Vanguard Group, Inc.; FMR LLC; Impactive Capital LP | I51: IQTR1887698908 | J51: 2024-07-11 | K51: Software and Services (Primary) | L51: 1307.7 | M51: 2024-11-25 | N51: - | O51: Acquisition of Majority Stake; Cash Merger; Equity Reinvestment; Going Private Transaction; Leveraged Buy Out (LBO)
A52: 2023-06-06 | B52: 360 Security Technology Inc. (SHSE:601360) | C52: SHSE:601360 | D52: Merger/Acquisition | E52: Closed | F52: - | G52: - | H52: - | I52: IQTR1841667695 | J52: 2023-06-06 | K52: Software and Services (Primary) | L52: 1304.5 | M52: 2023-06-05 | N52: 19 | O52: Acquisition of Minority Stake; Individual Investors Participated; Terms Not Disclosed
A53: 2021-11-22 | B53: Vonage Holdings Corp. | C53: - | D53: Merger/Acquisition | E53: Closed | F53: 6364.26 | G53: Telefonaktiebolaget LM Ericsson (publ) (OM:ERIC B) | H53: BlackRock, Inc. (NYSE:BLK); The Vanguard Group, Inc.; JANA Partners LLC; Janus Henderson Group Ltd. | I53: IQTR1759281617 | J53: 2021-11-22 | K53: Software and Services (Primary) | L53: 1295.67 | M53: 2022-07-21 | N53: - | O53: Acquisition of Majority Stake; Cash Merger; Cross-Border
A54: 2024-11-04 | B54: CoreWeave, Inc. (NasdaqGS:CRWV) | C54: NasdaqGS:CRWV | D54: Merger/Acquisition | E54: Closed | F54: 0.25 | G54: Blick Global Group AB (publ) (NGM:BLICK) | H54: - | I54: IQTR1903241894 | J54: 2024-11-04 | K54: Software and Services (Primary) | L54: 1283.99 | M54: 2024-11-01 | N54: 3789 | O54: Acquisition of Minority Stake; Cross-Border
A55: 2025-07-30 | B55: CyberArk Software Ltd. | C55: - | D55: Merger/Acquisition | E55: Closed | F55: 26153.37 | G55: Athens Strategies Ltd | H55: FMR LLC | I55: IQTR1955108370 | J55: 2025-07-30 | K55: Software and Services (Primary) | L55: 1200.12 | M55: 2026-02-11 | N55: -2.9 | O55: Acquisition of Majority Stake
A56: 2023-12-12 | B56: SII S.A. | C56: - | D56: Merger/Acquisition | E56: Closed | F56: 654.83 | G56: - | H56: - | I56: IQTR1888394514 | J56: 2023-12-12 | K56: Software and Services (Primary) | L56: 1146.93 | M56: 2024-02-23 | N56: - | O56: Acquisition of Minority Stake; Going Private Transaction; Management Participated; Minority Shareholder Increasing Ownership Stake; Squeeze Out / Short Form Merger; Tender Offer; Tender Offer (Full Bid)
A57: 2024-11-05 | B57: Aspen Technology, Inc. | C57: - | D57: Merger/Acquisition | E57: Closed | F57: 7350.58 | G57: Emerson Electric Co. (NYSE:EMR) | H57: Elliott Investment Management L.P. | I57: IQTR1903107882 | J57: 2024-11-05 | K57: Software and Services (Primary) | L57: 1140.44 | M57: 2025-03-12 | N57: 437.4 | O57: Acquisition of Minority Stake; Cash Merger; Majority Shareholder Increasing Ownership Stake; Majority Shareholder Purchasing Remaining Shares; Squeeze Out / Short Form Merger; Tender Offer; Tender Offer (Full Bid)
A58: 2025-12-08 | B58: Confluent, Inc. | C58: - | D58: Merger/Acquisition | E58: Closed | F58: 12753.02 | G58: International Business Machines Corporation (NYSE:IBM) | H58: Battery Ventures L.P.; Benchmark; Sequoia Capital Operations LLC; Index Ventures SA; The Vanguard Group, Inc.; Point72 Asset Management, L.P.; Trouvaille ANK Trust; Junípero Capital | I58: IQTR1973474553 | J58: 2025-12-08 | K58: Software and Services (Primary) | L58: 1113.15 | M58: 2026-03-17 | N58: -338 | O58: Acquisition of Majority Stake; Cash Merger
A59: 2024-05-13 | B59: Squarespace, Inc. | C59: - | D59: Merger/Acquisition | E59: Closed | F59: 7628.31 | G59: Accel Management Co, Inc.; General Atlantic Service Company, L.P.; Permira Advisers LLC | H59: Accel Management Co, Inc.; General Atlantic Service Company, L.P.; The Vanguard Group, Inc.; Wellington Management Group LLP; Glazer Capital, LLC; Dragoneer Investment Group, LLC | I59: IQTR1880889937 | J59: 2024-05-13 | K59: Software and Services (Primary) | L59: 1105.7 | M59: 2024-10-17 | N59: - | O59: Acquisition of Majority Stake; Cash Merger; Equity Reinvestment; Going Private Transaction; Leveraged Buy Out (LBO); Management Participated; Tender Offer; Tender Offer (Full Bid)
A60: 2023-04-21 | B60: Software GmbH | C60: - | D60: Merger/Acquisition | E60: Closed | F60: 2819.49 | G60: Silver Lake Technology Management, L.L.C. | H60: Bain Capital, LP; Software AG Stiftung; Rocket Software International (Uk) Limited | I60: IQTR1834779592 | J60: 2023-04-21 | K60: Software and Services (Primary) | L60: 1074.5 | M60: 2023-09-28 | N60: - | O60: Acquisition of Majority Stake; Cross-Border; Leveraged Buy Out (LBO); Tender Offer; Tender Offer (Full Bid)
A61: 2023-12-18 | B61: Software GmbH | C61: - | D61: Merger/Acquisition | E61: Closed | F61: 172.56 | G61: Silver Lake Technology Management, L.L.C. | H61: - | I61: IQTR1870160384 | J61: 2023-12-18 | K61: Software and Services (Primary) | L61: 1049.43 | M61: 2024-02-23 | N61: - | O61: Acquisition of Minority Stake; Cash Merger; Cross-Border; Going Private Transaction; Majority Shareholder Increasing Ownership Stake; Majority Shareholder Purchasing Remaining Shares; Squeeze Out / Short Form Merger; Tender Offer; Tender Offer (Full Bid)
A62: 2023-10-23 | B62: Software GmbH | C62: - | D62: Merger/Acquisition | E62: Closed | F62: - | G62: Silver Lake Technology Management, L.L.C.; Software GmbH | H62: - | I62: IQTR1859816481 | J62: 2023-10-23 | K62: Software and Services (Primary) | L62: 1049.43 | M62: 2023-10-23 | N62: - | O62: Acquisition of Minority Stake; Cross-Border; Majority Shareholder Increasing Ownership Stake; Terms Not Disclosed
A63: 2024-09-24 | B63: Smartsheet Inc. | C63: - | D63: Merger/Acquisition | E63: Closed | F63: 7989.56 | G63: Vista Equity Partners Management, LLC; Blackstone Management Partners L.L.C.; Platinum Falcon B 2018 Rsc Ltd | H63: Alamar Capital Management, LLC | I63: IQTR1898365319 | J63: 2024-09-24 | K63: Software and Services (Primary) | L63: 1042.26 | M63: 2025-01-22 | N63: -22.2 | O63: Acquisition of Majority Stake; Cross-Border; Go Shop Provision; Going Private Transaction; Leveraged Buy Out (LBO); Minority Shareholder Increasing Ownership Stake
A64: 2024-08-05 | B64: Thoughtworks Holding, Inc. | C64: - | D64: Merger/Acquisition | E64: Closed | F64: 642.04 | G64: Apax Partners LLP; Turing EquityCo II L.P. | H64: Siemens AG; Fabric Ventures Group S.à r.l.; IOSG Ventures; Turing EquityCo II L.P. | I64: IQTR1890448244 | J64: 2024-08-05 | K64: Software and Services (Primary) | L64: 1032.81 | M64: 2024-11-13 | N64: - | O64: Acquisition of Minority Stake; Cash Merger; Cross-Border; Equity Reinvestment; Going Private Transaction
A65: 2024-01-16 | B65: AsiaInfo Technologies Limited (SEHK:1675) | C65: SEHK:1675 | D65: Merger/Acquisition | E65: Closed | F65: 188.18 | G65: Asiainfo Security Technologies Co.,Ltd. (SHSE:688225) | H65: Skipper Investment Limited | I65: IQTR1868785095 | J65: 2024-01-16 | K65: Software and Services (Primary) | L65: 1015.65 | M65: 2024-11-08 | N65: -13.6 | O65: Acquisition of Minority Stake
A66: 2024-07-24 | B66: Seidor, S.A. | C66: - | D66: Merger/Acquisition | E66: Closed | F66: - | G66: The Carlyle Group Inc. (NasdaqGS:CG) | H66: - | I66: IQTR1888805094 | J66: 2024-07-24 | K66: Software and Services (Primary) | L66: 970.37 | M66: 2025-02-27 | N66: - | O66: Acquisition of Majority Stake; Cross-Border; Family Succession; Leveraged Buy Out (LBO)
A67: 2021-10-14 | B67: Devoteam SA | C67: - | D67: Merger/Acquisition | E67: Closed | F67: 336.88 | G67: Devoteam Group SAS | H67: - | I67: IQTR1685197722 | J67: 2021-10-14 | K67: Software and Services (Primary) | L67: 952.34 | M67: 2021-12-22 | N67: - | O67: Acquisition of Minority Stake; Cash Merger; Majority Shareholder Increasing Ownership Stake; Majority Shareholder Purchasing Remaining Shares; Squeeze Out / Short Form Merger; Tender Offer; Tender Offer (Full Bid)
A68: 2023-07-31 | B68: New Relic, Inc. | C68: - | D68: Merger/Acquisition | E68: Closed | F68: 7054.24 | G68: TPG Capital, L.P.; Francisco Partners Management, L.P. | H68: The Vanguard Group, Inc.; Eminence Capital, LP; JANA Partners LLC; HMI Capital Management, L.P. | I68: IQTR1849534437 | J68: 2023-07-31 | K68: Software and Services (Primary) | L68: 951.8 | M68: 2023-11-08 | N68: - | O68: Acquisition of Majority Stake; Cash Merger; Go Shop Provision; Going Private Transaction; Leveraged Buy Out (LBO); Management Participated
A69: 2023-12-18 | B69: Alteryx, Inc. | C69: - | D69: Merger/Acquisition | E69: Closed | F69: 5027.93 | G69: Insight Venture Management, LLC; Clearlake Capital Group, L.P. | H69: BlackRock, Inc. (NYSE:BLK); The Vanguard Group, Inc. | I69: IQTR1865270098 | J69: 2023-12-18 | K69: Software and Services (Primary) | L69: 920.35 | M69: 2024-03-19 | N69: - | O69: Acquisition of Majority Stake; Cash Merger; Going Private Transaction; Leveraged Buy Out (LBO)
A70: 2021-12-31 | B70: Glovoapp23, S.L. | C70: - | D70: Merger/Acquisition | E70: Closed | F70: 880.47 | G70: Delivery Hero SE (XTRA:DHER) | H70: - | I70: IQTR1763140911 | J70: 2021-12-31 | K70: Software and Services (Primary) | L70: 909.81 | M70: 2022-07-04 | N70: - | O70: Acquisition of Minority Stake; Cross-Border; Minority Shareholder Gaining Majority Control; Minority Shareholder Increasing Ownership Stake
A71: 2024-02-27 | B71: Perficient, Inc. | C71: - | D71: Merger/Acquisition | E71: Closed | F71: 2877.57 | G71: EQT Private Capital Asia | H71: BlackRock, Inc. (NYSE:BLK); The Vanguard Group, Inc.; Wellington Management Group LLP | I71: IQTR1880250753 | J71: 2024-02-27 | K71: Software and Services (Primary) | L71: 906.54 | M71: 2024-10-02 | N71: - | O71: Acquisition of Majority Stake; Cash Merger; Cross-Border; Going Private Transaction; Leveraged Buy Out (LBO)
A72: 2025-08-25 | B72: Verint Systems Inc. (NasdaqGS:VRNT) | C72: NasdaqGS:VRNT | D72: Merger/Acquisition | E72: Closed | F72: 2233.83 | G72: Calabrio, Inc. | H72: Apax Partners LLP; Neuberger Berman BD LLC; Inventures Group; Jericho Capital Corp.; Forum Ventures, LLC; L Marks Ltd. | I72: IQTR1958114138 | J72: 2025-08-25 | K72: Software and Services (Primary) | L72: 893.84 | M72: 2025-11-26 | N72: - | O72: Acquisition of Majority Stake; Cash Merger
A73: 2024-07-08 | B73: TeamSystem Holding S.p.A. | C73: - | D73: Merger/Acquisition | E73: Closed | F73: - | G73: Hellman & Friedman LLC | H73: HgCapital LLP | I73: IQTR1887388288 | J73: 2024-07-08 | K73: Software and Services (Primary) | L73: 874.25 | M73: 2024-09-06 | N73: 390.5 | O73: Acquisition of Minority Stake; Cross-Border; Majority Shareholder Increasing Ownership Stake; Terms Not Disclosed
A74: 2024-07-03 | B74: Keywords Studios plc | C74: - | D74: Merger/Acquisition | E74: Closed | F74: 2959.77 | G74: EQT Private Capital Asia; CPP Investment Board Private Holdings (4) Inc.; Rosa Investments Pte. Ltd | H74: Banque Pictet & Cie SA; Franklin Templeton Institutional, LLC | I74: IQTR1886607085 | J74: 2024-07-03 | K74: Software and Services (Primary) | L74: 863.38 | M74: 2024-10-23 | N74: - | O74: Acquisition of Majority Stake; Cash Merger; Cross-Border; Sponsor/Strategic JV Acquisition
A75: 2022-12-12 | B75: Coupa Software Incorporated | C75: - | D75: Merger/Acquisition | E75: Closed | F75: 9053.72 | G75: Abu Dhabi Investment Authority; Thoma Bravo, L.P. | H75: BlackRock, Inc. (NYSE:BLK); The Vanguard Group, Inc.; Viking Global Investors LP; T. Rowe Price Associates, Inc. | I75: IQTR1818367875 | J75: 2022-12-12 | K75: Software and Services (Primary) | L75: 818.11 | M75: 2023-02-28 | N75: - | O75: Acquisition of Majority Stake; Cash Merger; Cross-Border; Going Private Transaction; Leveraged Buy Out (LBO)
A76: 2021-09-13 | B76: The Rocket Science Group, LLC | C76: - | D76: Merger/Acquisition | E76: Closed | F76: 11761.32 | G76: Intuit Inc. (NasdaqGS:INTU) | H76: DMK Life LLC; DMK 10 LLC; DMK 20 LLC | I76: IQTR1681371335 | J76: 2021-09-13 | K76: Software and Services (Primary) | L76: 800 | M76: 2021-11-01 | N76: - | O76: Acquisition of Majority Stake
A77: 2025-02-07 | B77: SolarWinds Corporation | C77: - | D77: Merger/Acquisition | E77: Closed | F77: 4678.82 | G77: Turn/River Management, L.P. | H77: Silver Lake Technology Management, L.L.C.; BlackRock, Inc. (NYSE:BLK); Thoma Bravo, L.P. | I77: IQTR1930453238 | J77: 2025-02-07 | K77: Software and Services (Primary) | L77: 796.9 | M77: 2025-04-16 | N77: 273.5 | O77: Acquisition of Majority Stake; Cash Merger; Going Private Transaction; Leveraged Buy Out (LBO)
A78: 2022-08-08 | B78: Avalara, Inc. | C78: - | D78: Merger/Acquisition | E78: Closed | F78: 9831.35 | G78: Vista Equity Partners Management, LLC | H78: Franklin Templeton Inc. (NYSE:BEN); BlackRock, Inc. (NYSE:BLK); The Vanguard Group, Inc.; Wellington Management Group LLP | I78: IQTR1795821068 | J78: 2022-08-08 | K78: Software and Services (Primary) | L78: 789.43 | M78: 2022-10-19 | N78: - | O78: Acquisition of Majority Stake; Cash Merger; Going Private Transaction; Leveraged Buy Out (LBO)
A79: 2025-10-21 | B79: Digital Value S.p.A. | C79: - | D79: Merger/Acquisition | E79: Closed | F79: 296.88 | G79: OEP Capital Advisors L.P. | H79: DV Holding S.p.A. | I79: IQTR1966885655 | J79: 2025-10-21 | K79: Software and Services (Primary) | L79: 783.55 | M79: 2026-03-05 | N79: 52.5 | O79: Acquisition of Majority Stake; Cross-Border; Leveraged Buy Out (LBO)
A80: 2025-10-21 | B80: Digital Value S.p.A. | C80: - | D80: Merger/Acquisition | E80: Closed | F80: 139.57 | G80: OEP Capital Advisors L.P. | H80: - | I80: IQTR1988620140 | J80: 2025-10-21 | K80: Software and Services (Primary) | L80: 783.55 | M80: 2026-05-27 | N80: 52.5 | O80: Acquisition of Minority Stake; Cross-Border; Tender Offer; Tender Offer (Full Bid)
A81: 2026-01-23 | B81: Circle8 Group | C81: - | D81: Merger/Acquisition | E81: Closed | F81: 275.74 | G81: Circle8 Group, Inc. (NasdaqGM:CIRC) | H81: Axiom Partners GmbH | I81: IQTR1980096310 | J81: 2026-01-23 | K81: Software and Services (Primary) | L81: 780 | M81: 2026-01-23 | N81: - | O81: Acquisition of Majority Stake; Cross-Border
A82: 2023-06-07 | B82: WinTriX DC Group | C82: - | D82: Merger/Acquisition | E82: Closed | F82: 4484.95 | G82: Bain Capital Investors, LLC | H82: APG Asset Management NV | I82: IQTR1841959978 | J82: 2023-06-07 | K82: Software and Services (Primary) | L82: 770.83 | M82: 2023-12-18 | N82: - | O82: Acquisition of Majority Stake; Cash Merger; Cross-Border; Going Private Transaction; Leveraged Buy Out (LBO); Minority Shareholder Increasing Ownership Stake; Minority Shareholder Purchasing Remaining Shares; Tender Offer; Tender Offer (Full Bid)
A83: 2026-05-13 | B83: LINK Mobility Group Holding ASA (OB:LINK) | C83: OB:LINK | D83: Merger/Acquisition | E83: Closed | F83: 118.3 | G83: - | H83: Victory Partners VIII Limited | I83: IQTR2000553888 | J83: 2026-05-13 | K83: Software and Services (Primary) | L83: 763.63 | M83: 2026-05-13 | N83: 91.3 | O83: Acquisition of Minority Stake
A84: 2024-05-28 | B84: Ebix, Inc. | C84: - | D84: Merger/Acquisition | E84: Closed | F84: 831.85 | G84: EBIX Limited (BSE:531035); Vikas Lifecare Limited (NSEI:VIKASLIFE); Vitasta Software India Private Limited | H84: - | I84: IQTR1885559196 | J84: 2024-05-28 | K84: Software and Services (Primary) | L84: 735.63 | M84: 2024-08-30 | N84: - | O84: Acquisition of Majority Stake; Bankruptcy Sale; Cash Merger; Creation of Joint Venture; Cross-Border
A85: 2021-10-11 | B85: AspenTech Corporation | C85: - | D85: Merger/Acquisition | E85: Closed | F85: 6339.12 | G85: Emerson Electric Co. (NYSE:EMR) | H85: - | I85: IQTR1684909762 | J85: 2021-10-11 | K85: Software and Services (Primary) | L85: 730.43 | M85: 2022-05-16 | N85: - | O85: Acquisition of Majority Stake
A86: 2024-04-25 | B86: AssetMark Financial Holdings, Inc. | C86: - | D86: Merger/Acquisition | E86: Closed | F86: 2739.56 | G86: GTCR LLC | H86: Huatai International Investment Holdings Limited | I86: IQTR1879103295 | J86: 2024-04-25 | K86: Software and Services (Primary) | L86: 728.47 | M86: 2024-09-05 | N86: - | O86: Acquisition of Majority Stake; Cash Merger; Going Private Transaction; Leveraged Buy Out (LBO)
A87: 2022-01-17 | B87: Yunex GmbH | C87: - | D87: Merger/Acquisition | E87: Closed | F87: 1083.73 | G87: Mundys S.p.A. | H87: Siemens Mobility GmbH | I87: IQTR1764591672 | J87: 2022-01-17 | K87: Software and Services (Primary) | L87: 724.85 | M87: 2022-06-30 | N87: - | O87: Acquisition of Majority Stake; Cash Merger; Corporate Divestiture; Cross-Border
A88: 2023-06-19 | B88: Foxway AB | C88: - | D88: Merger/Acquisition | E88: Closed | F88: - | G88: Nordic Capital | H88: - | I88: IQTR1844194992 | J88: 2023-06-19 | K88: Software and Services (Primary) | L88: 708.04 | M88: 2023-10-05 | N88: -9.1 | O88: Acquisition of Majority Stake; Leveraged Buy Out (LBO); Terms Not Disclosed
A89: 2022-06-21 | B89: Venustech Group Inc. (SZSE:002439) | C89: SZSE:002439 | D89: Merger/Acquisition | E89: Closed | F89: 618.59 | G89: China Mobile Capital Co Ltd | H89: - | I89: IQTR1787619875 | J89: 2022-06-21 | K89: Software and Services (Primary) | L89: 701.06 | M89: 2022-06-21 | N89: -29.4 | O89: Acquisition of Minority Stake
A90: 2025-10-29 | B90: Jamf Holding Corp. | C90: - | D90: Merger/Acquisition | E90: Closed | F90: 2735.68 | G90: Francisco Partners Management, L.P. | H90: The Vanguard Group, Inc.; Vista Equity Partners Management, LLC | I90: IQTR1967918116 | J90: 2025-10-29 | K90: Software and Services (Primary) | L90: 690.59 | M90: 2026-01-30 | N90: 38.3 | O90: Acquisition of Majority Stake; Cash Merger; Going Private Transaction; Leveraged Buy Out (LBO)
A91: 2026-04-13 | B91: Reliance Projects & Property Management Services Limited | C91: - | D91: Merger/Acquisition | E91: Closed | F91: 29.26 | G91: Jaipur Enclave Private Ltd | H91: Reliance Retail Limited | I91: IQTR1995264367 | J91: 2026-04-13 | K91: Software and Services (Primary) | L91: 684.83 | M91: 2026-04-13 | N91: - | O91: Acquisition of Majority Stake; Cash Merger; Corporate Divestiture
A92: 2025-09-11 | B92: LINK Mobility Group Holding ASA (OB:LINK) | C92: OB:LINK | D92: Merger/Acquisition | E92: Closed | F92: 52.74 | G92: - | H92: Karbon Invest AS | I92: IQTR1960281017 | J92: 2025-09-11 | K92: Software and Services (Primary) | L92: 683.55 | M92: 2025-09-11 | N92: 91.3 | O92: Acquisition of Minority Stake
A93: 2023-08-17 | B93: TeamSystem Holding S.p.A. | C93: - | D93: Merger/Acquisition | E93: Closed | F93: - | G93: Abu Dhabi Investment Authority; CapitalG Management Company, LLC | H93: HgCapital LLP | I93: IQTR1852944845 | J93: 2023-08-17 | K93: Software and Services (Primary) | L93: 676.57 | M93: 2024-03-31 | N93: 390.5 | O93: Acquisition of Minority Stake; Cross-Border; Terms Not Disclosed
A94: 2023-08-17 | B94: SUSE S.A. | C94: - | D94: Merger/Acquisition | E94: Closed | F94: 621.94 | G94: SUSE S.A. | H94: - | I94: IQTR1853092713 | J94: 2023-08-17 | K94: Software and Services (Primary) | L94: 672.92 | M94: 2023-11-13 | N94: - | O94: Acquisition of Minority Stake; Cash Merger; Majority Shareholder Increasing Ownership Stake; Majority Shareholder Purchasing Remaining Shares; Tender Offer; Tender Offer (Full Bid)
A95: 2022-07-13 | B95: ironSource Ltd. | C95: - | D95: Merger/Acquisition | E95: Closed | F95: 4740.32 | G95: Unity Software Inc. (NYSE:U) | H95: Viola Ventures; App Investments S.à R.l. | I95: IQTR1791060882 | J95: 2022-07-13 | K95: Software and Services (Primary) | L95: 671.17 | M95: 2022-11-07 | N95: - | O95: Acquisition of Majority Stake; Cross-Border; Stock Merger
A96: 2025-10-30 | B96: Bending Spoons S.p.A. (NasdaqGS:BSP) | C96: NasdaqGS:BSP | D96: Merger/Acquisition | E96: Closed | F96: 31.22 | G96: - | H96: Tamburi Investment Partners S.p.A. (BIT:TIP) | I96: IQTR1968615496 | J96: 2025-10-30 | K96: Software and Services (Primary) | L96: 671.05 | M96: 2025-10-30 | N96: 946.5 | O96: Acquisition of Minority Stake
A97: 2024-12-19 | B97: Crayon Group Holding ASA | C97: - | D97: Merger/Acquisition | E97: Closed | F97: 1254.54 | G97: SoftwareOne Holding AG (SWX:SWON) | H97: - | I97: IQTR1913479166 | J97: 2024-12-19 | K97: Software and Services (Primary) | L97: 662.29 | M97: 2025-07-02 | N97: 81.9 | O97: Acquisition of Majority Stake; Cross-Border; Squeeze Out / Short Form Merger; Tender Offer; Tender Offer (Full Bid)
A98: 2024-04-26 | B98: Darktrace Limited | C98: - | D98: Merger/Acquisition | E98: Closed | F98: 5591.6 | G98: Thoma Bravo, L.P. | H98: Insight Venture Management, LLC; KKR & Co. Inc. (NYSE:KKR); Summit Partners, L.P.; SoftBank Capital; Vitruvian Partners LLP; Balderton Capital (UK) LLP; Invoke Capital; Hoxton Ventures LLP; Ten Eleven Ventures, LLC; KKR Dark Aggregator L.P. | I98: IQTR1879230826 | J98: 2024-04-26 | K98: Software and Services (Primary) | L98: 653.95 | M98: 2024-10-01 | N98: - | O98: Acquisition of Majority Stake; Cash Merger; Cross-Border; Going Private Transaction; Leveraged Buy Out (LBO)
A99: 2024-10-30 | B99: Altair Engineering Inc. | C99: - | D99: Merger/Acquisition | E99: Closed | F99: 10700.92 | G99: Siemens Product Lifecycle Management Software Inc. | H99: BlackRock, Inc. (NYSE:BLK); The Vanguard Group, Inc.; Matrix Capital Management Company, LP; JRS Investments LLC; Pictet Asset Management SA | I99: IQTR1902476016 | J99: 2024-10-30 | K99: Software and Services (Primary) | L99: 644.66 | M99: 2025-03-26 | N99: 60.3 | O99: Acquisition of Majority Stake; Cash Merger
A100: 2022-04-11 | B100: Datto Holding Corp. | C100: - | D100: Merger/Acquisition | E100: Closed | F100: 6219.6 | G100: Kaseya Inc. | H100: Vista Equity Partners Management, LLC | I100: IQTR1777910955 | J100: 2022-04-11 | K100: Software and Services (Primary) | L100: 644.53 | M100: 2022-06-23 | N100: - | O100: Acquisition of Majority Stake; Cash Merger
...
