Workbook

Sheet Assumptions
A1: LBO MODEL - ASSUMPTIONS
A3: Company Name: | B3: Linedata Services S.A.
A4: Ticker: | B4: LIN
A6: YEAR 0 DATA (Current LTM)
A7: Current Revenue (LTM): | B7: 189 | C7: $M
A8: Current EBITDA (LTM): | B8: 30.7 | C8: $M
A9: Current EBITDA Margin: | B9: 0.162 | C9: %
A10: Current Debt: | B10: 109.3 | C10: $M
A12: ENTRY VALUATION
A13: Entry Multiple (EV/EBITDA): | B13: 11.69 | C13: x
A14: Enterprise Value at Entry: | B14: =B8*B13 -> 358.883 | C14: $M
A16: CAPITAL STRUCTURE (40% Equity, 60% Debt)
A17: Sponsor Equity Investment in percent: | B17: 0.4 | C17: %
A18: Debt Investment in percent: | B18: =1-B17 -> 0.6 | C18: %
A19: Sponsor Equity Investment: | B19: =B14*B17 -> 143.5532 | C19: $M
A20: Total Debt to Raise: | B20: =B14*B18 -> 215.3298 | C20: $M
A21: Entry Leverage (Debt/EBITDA): | B21: =B20/B8 -> 7.014 | C21: x EBITDA
A22: Senior Debt (71% of total): | B22: =B20*0.71 -> 152.88416 | C22: $M
A23: Sub Debt (29% of total): | B23: =B20*0.29 -> 62.445642 | C23: $M
A25: DEBT RATES
A26: Senior Debt Rate: | B26: 0.063 | C26: %
A27: Sub Debt Rate: | B27: 0.0885 | C27: %
A29: 5-YEAR PROJECTIONS
A30: Revenue Growth Rate (Yr 1): | B30: 0.0265 | C30: %
A31: Revenue Growth Rate (Yr 2): | B31: 0.0302 | C31: %
A32: Revenue Growth Rate (Yr 3-5): | B32: =AVERAGE(B30:B31) -> 0.02835 | C32: %
A33: EBITDA Margin (holds constant): | B33: =B9 -> 0.162 | C33: %
A34: D&A % of Revenue: | B34: 0.0804 | C34: %
A35: Tax Rate: | B35: 0.275 | C35: %
A36: FCF Sweep % (amount to debt paydown) | B36: 0.75 | C36: %
A37: Capital Expenditures (CapEx) as a percentage of Revenue | B37: 0.02 | C37: %
A38: Change in working capital % | B38: 0 | C38: %
A40: EXIT ASSUMPTIONS (YEAR 5)
A41: Exit Multiple (EV/EBITDA): | B41: =B13 -> 11.69 | C41: x

Sheet Income_Statement
A1: 5-YEAR INCOME STATEMENT
A3: Line Item | B3: Year 0 | C3: Year 1 | D3: Year 2 | E3: Year 3 | F3: Year 4 | G3: Year 5
A4: Revenue | B4: =Assumptions!B7 -> 189 | C4: =B4*(1+Assumptions!B30) -> 194.0085 | D4: =C4*(1+Assumptions!B31) -> 199.86756 | E4: =D4*(1+Assumptions!B32) -> 205.5338 | F4: =E4*(1+Assumptions!B32) -> 211.36069 | G4: =F4*(1+Assumptions!B32) -> 217.35276
A5: EBITDA | B5: =B4*Assumptions!$B$33 -> 30.618 | C5: =C4*Assumptions!$B$33 -> 31.429377 | D5: =D4*Assumptions!$B$33 -> 32.378544 | E5: =E4*Assumptions!$B$33 -> 33.296476 | F5: =F4*Assumptions!$B$33 -> 34.240431 | G5: =G4*Assumptions!$B$33 -> 35.211147
A6: EBITDA Margin % | B6: =B5/B4 -> 0.162 | C6: =C5/C4 -> 0.162 | D6: =D5/D4 -> 0.162 | E6: =E5/E4 -> 0.162 | F6: =F5/F4 -> 0.162 | G6: =G5/G4 -> 0.162
A7: D&A | B7: =B4*Assumptions!$B$34 -> 15.1956 | C7: =C4*Assumptions!$B$34 -> 15.598283 | D7: =D4*Assumptions!$B$34 -> 16.069352 | E7: =E4*Assumptions!$B$34 -> 16.524918 | F7: =F4*Assumptions!$B$34 -> 16.993399 | G7: =G4*Assumptions!$B$34 -> 17.475162
A8: EBIT (EBITDA - D&A) | B8: =B5-B7 -> 15.4224 | C8: =C5-C7 -> 15.831094 | D8: =D5-D7 -> 16.309193 | E8: =E5-E7 -> 16.771558 | F8: =F5-F7 -> 17.247032 | G8: =G5-G7 -> 17.735985
A10: Interest Expense - Senior | B10: =Debt_Schedule!B6*Assumptions!$B$26 -> 9.631702 | C10: =Debt_Schedule!C6*Assumptions!$B$26 -> 9.631702 | D10: =Debt_Schedule!D6*Assumptions!$B$26 -> 9.0549683 | E10: =Debt_Schedule!E6*Assumptions!$B$26 -> 8.4253788 | F10: =Debt_Schedule!F6*Assumptions!$B$26 -> 7.7422122 | G10: =Debt_Schedule!G6*Assumptions!$B$26 -> 7.0027255
A11: Interest Expense - Sub | B11: =Debt_Schedule!B11*Assumptions!$B$27 -> 5.5264393 | C11: =Debt_Schedule!C11*Assumptions!$B$27 -> 5.5264393 | D11: =Debt_Schedule!D11*Assumptions!$B$27 -> 5.5264393 | E11: =Debt_Schedule!E11*Assumptions!$B$27 -> 5.5264393 | F11: =Debt_Schedule!F11*Assumptions!$B$27 -> 5.5264393 | G11: =Debt_Schedule!G11*Assumptions!$B$27 -> 5.5264393
A12: Total Interest | B12: =B10+B11 -> 15.158141 | C12: =C10+C11 -> 15.158141 | D12: =D10+D11 -> 14.581408 | E12: =E10+E11 -> 13.951818 | F12: =F10+F11 -> 13.268651 | G12: =G10+G11 -> 12.529165
A13: EBT (EBIT - Interest) | B13: =B8-B12 -> 0.26425873 | C13: =C8-C12 -> 0.67295233 | D13: =D8-D12 -> 1.727785 | E13: =E8-E12 -> 2.8197401 | F13: =F8-F12 -> 3.9783804 | G13: =G8-G12 -> 5.2068204
A14: Taxes | B14: =B13*Assumptions!$B$35 -> 0.07267115 | C14: =C13*Assumptions!$B$35 -> 0.18506189 | D14: =D13*Assumptions!$B$35 -> 0.47514089 | E14: =E13*Assumptions!$B$35 -> 0.77542853 | F14: =F13*Assumptions!$B$35 -> 1.0940546 | G14: =G13*Assumptions!$B$35 -> 1.4318756
A15: Net Income | B15: =B13-B14 -> 0.19158758 | C15: =C13-C14 -> 0.48789044 | D15: =D13-D14 -> 1.2526442 | E15: =E13-E14 -> 2.0443116 | F15: =F13-F14 -> 2.8843258 | G15: =G13-G14 -> 3.7749448
A17: Interest Paid | B17: =B12 -> 15.158141 | C17: =C12 -> 15.158141 | D17: =D12 -> 14.581408 | E17: =E12 -> 13.951818 | F17: =F12 -> 13.268651 | G17: =G12 -> 12.529165
A18: CAPEX | B18: =B4*Assumptions!$B$37 -> 3.78 | C18: =C4*Assumptions!$B$37 -> 3.88017 | D18: =D4*Assumptions!$B$37 -> 3.9973511 | E18: =E4*Assumptions!$B$37 -> 4.110676 | F18: =F4*Assumptions!$B$37 -> 4.2272137 | G18: =G4*Assumptions!$B$37 -> 4.3470552
A19: Change in Working Capital | B19: =B4*Assumptions!$B$38 -> 0 | C19: =C4*Assumptions!$B$38 -> 0 | D19: =D4*Assumptions!$B$38 -> 0 | E19: =E4*Assumptions!$B$38 -> 0 | F19: =F4*Assumptions!$B$38 -> 0 | G19: =G4*Assumptions!$B$38 -> 0
A20: Taxes | B20: =B14 -> 0.07267115 | C20: =C14 -> 0.18506189 | D20: =D14 -> 0.47514089 | E20: =E14 -> 0.77542853 | F20: =F14 -> 1.0940546 | G20: =G14 -> 1.4318756
A21: EBITDA | B21: =B5 -> 30.618 | C21: =C5 -> 31.429377 | D21: =D5 -> 32.378544 | E21: =E5 -> 33.296476 | F21: =F5 -> 34.240431 | G21: =G5 -> 35.211147
A22: FCF | B22: =B21-B20-B19-B18-B17 -> 11.607188 | C22: =C21-C20-C19-C18-C17 -> 12.206004 | D22: =D21-D20-D19-D18-D17 -> 13.324645 | E22: =E21-E20-E19-E18-E17 -> 14.458553 | F22: =F21-F20-F19-F18-F17 -> 15.650511 | G22: =G21-G20-G19-G18-G17 -> 16.903052

Sheet Debt_Schedule
A1: DEBT PAYDOWN SCHEDULE
A3: Line Item | B3: Year 0 | C3: Year 1 | D3: Year 2 | E3: Year 3 | F3: Year 4 | G3: Year 5
A5: SENIOR DEBT
A6: Beginning Balance | B6: =Assumptions!B22 -> 152.88416 | C6: =B7 -> 152.88416 | D6: =C7 -> 143.72966 | E6: =D7 -> 133.73617 | F6: =E7 -> 122.89226 | G6: =F7 -> 111.15437
A7: Ending Balance | B7: =B6 -> 152.88416 | C7: =B7-Income_Statement!C22*Assumptions!$B$36 -> 143.72966 | D7: =C7-Income_Statement!D22*Assumptions!$B$36 -> 133.73617 | E7: =D7-Income_Statement!E22*Assumptions!$B$36 -> 122.89226 | F7: =E7-Income_Statement!F22*Assumptions!$B$36 -> 111.15437 | G7: =F7-Income_Statement!G22*Assumptions!$B$36 -> 98.477085
A10: SUBORDINATED DEBT
A11: Beginning Balance | B11: =Assumptions!B23 -> 62.445642 | C11: =B12 -> 62.445642 | D11: =C12 -> 62.445642 | E11: =D12 -> 62.445642 | F11: =E12 -> 62.445642 | G11: =F12 -> 62.445642
A12: Ending Balance | B12: =B11 -> 62.445642 | C12: =C11 -> 62.445642 | D12: =D11 -> 62.445642 | E12: =E11 -> 62.445642 | F12: =F11 -> 62.445642 | G12: =G11 -> 62.445642
A15: TOTAL DEBT
A16: Total Debt | B16: =B7+B12 -> 215.3298 | C16: =C7+C12 -> 206.1753 | D16: =D7+D12 -> 196.18181 | E16: =E7+E12 -> 185.3379 | F16: =F7+F12 -> 173.60002 | G16: =G7+G12 -> 160.92273
A18: Leverage Ratio (Debt/EBITDA) | B18: =B16/Income_Statement!B5 -> 7.0327846 | C18: =C16/Income_Statement!C5 -> 6.5599549 | D18: =D16/Income_Statement!D5 -> 6.0590066 | E18: =E16/Income_Statement!E5 -> 5.5662917 | F18: =F16/Income_Statement!F5 -> 5.0700301 | G18: =G16/Income_Statement!G5 -> 4.5702211

Sheet Exit_Analysis
A1: EXIT ANALYSIS & RETURNS (YEAR 5)
A3: YEAR 5 VALUATION
A4: Year 5 Revenue | B4: =Income_Statement!G4 -> 217.35276
A5: Year 5 EBITDA | B5: =Income_Statement!G5 -> 35.211147
A6: Exit Multiple (EV/EBITDA) | B6: =Assumptions!B41 -> 11.69
A7: Exit Enterprise Value | B7: =B5*B6 -> 411.61831
A9: DEBT AT EXIT
A10: Senior Debt at Exit | B10: =Debt_Schedule!G7 -> 98.477085
A11: Sub Debt at Exit | B11: =Debt_Schedule!G12 -> 62.445642
A12: Total Debt at Exit | B12: =B10+B11 -> 160.92273
A14: EQUITY VALUE AT EXIT | B14: =B7-B12 -> 250.69558
A16: INITIAL EQUITY INVESTMENT | B16: =Assumptions!B19 -> 143.5532
A18: RETURNS ANALYSIS
A19: Money Multiple (MOIC) | B19: =B14/B16 -> 1.7463601
A20: IRR (%) | B20: =(B14/B16)^(1/5)-1 -> 0.11796128
A22: LEVERAGE ANALYSIS
A23: Entry Leverage (Debt/EBITDA) | B23: =Assumptions!B21 -> 7.014
A24: Exit Leverage (Debt/EBITDA) | B24: =B12/B5 -> 4.5702211
